Workbook
Name abortion: 'Entradas de población-año base'!$C$38
Name abortion: 'Entradas de población-año base'!$C$41
Name comm_deliv: 'Tratamiento de la MAS'!$D$3
Name diarrhoea_1_5mo: 'Entradas de población-año base'!$C$52
Name diarrhoea_12_23mo: 'Entradas de población-año base'!$C$54
Name diarrhoea_1mo: 'Entradas de población-año base'!$C$51
Name diarrhoea_24_59mo: 'Entradas de población-año base'!$C$55
Name diarrhoea_6_11mo: 'Entradas de población-año base'!$C$53
Name end_year: 'Entradas de población-año base'!$C$4
Name famplan_unmet_need: 'Entradas de población-año base'!$C$13
Name food_insecure: 'Entradas de población-año base'!$C$8
Name frac_children_health_facility: 'Entradas de población-año base'!$C$12
Name frac_diarrhea_severe: 'Entradas de población-año base'!$C$58
Name frac_maize: 'Entradas de población-año base'!$C$19
Name frac_malaria_risk: 'Entradas de población-año base'!$C$9
Name frac_mam_1_5months: 'Distribución estado nutricional'!$D$10
Name frac_mam_12_23months: 'Distribución estado nutricional'!$F$10
Name frac_mam_1month: 'Distribución estado nutricional'!$C$10
Name frac_mam_24_59months: 'Distribución estado nutricional'!$G$10
Name frac_mam_6_11months: 'Distribución estado nutricional'!$E$10
Name frac_MAMtoSAM: 'Entradas de población-año base'!#REF!
Name frac_other_staples: 'Entradas de población-año base'!$C$20
Name frac_PW_health_facility: 'Entradas de población-año base'!$C$11
Name frac_rice: 'Entradas de población-año base'!$C$17
Name frac_sam_1_5months: 'Distribución estado nutricional'!$D$11
Name frac_sam_12_23months: 'Distribución estado nutricional'!$F$11
Name frac_sam_1month: 'Distribución estado nutricional'!$C$11
Name frac_sam_24_59months: 'Distribución estado nutricional'!$G$11
Name frac_sam_6_11months: 'Distribución estado nutricional'!$E$11
Name frac_SAMtoMAM: 'Entradas de población-año base'!#REF!
Name frac_subsistence_farming: 'Entradas de población-año base'!$C$16
Name frac_wheat: 'Entradas de población-año base'!$C$18
Name infant_mortality: 'Entradas de población-año base'!$C$38
Name iron_deficiency_anaemia: 'Entradas de población-año base'!$C$59
Name manage_mam: 'Tratamiento de la MAS'!$D$2
Name maternal_mortality: 'Entradas de población-año base'!$C$40
Name neonatal_mortality: 'Entradas de población-año base'!$C$37
Name Percentage_of_pregnant_women_attending_health_facility: 'Entradas de población-año base'!$C$11
Name preterm_AGA: 'Entradas de población-año base'!$C$46
Name preterm_SGA: 'Entradas de población-año base'!$C$45
Name school_attendance: 'Entradas de población-año base'!$C$10
Name start_year: 'Entradas de población-año base'!$C$3
Name stillbirth: 'Entradas de población-año base'!$C$39
Name stillbirth: 'Entradas de población-año base'!$C$42
Name term_AGA: 'Entradas de población-año base'!$C$48
Name term_SGA: 'Entradas de población-año base'!$C$47
Name U5_mortality: 'Entradas de población-año base'!$C$39

Sheet Entradas de población-año base
A1: Datos del año de referencia | B1: Field | C1: Datos
A2: Años de proyección
B3: Año de referencia (año de inicio de la proyección) | C3: 2024
B4: Año final | C4: 2035
A6: Datos poblacionales
B7: Población infantil menor de 5 años | C7: 1169548.5
B8: Porcentaje de población con inseguridad alimentaria (pobre por defecto) | C8: 0.157
B9: Porcentaje de población con riesgo de malaria | C9: 0.01
B10: Asistencia a la escuela (porcentaje de mujeres de 15 a 19 años) | C10: 0.6352398
B11: Porcentaje de mujeres embarazadas que acuden a un centro de salud | C11: 1
B12: Porcentaje de niños que acuden a un centro de salud | C12: 1
B13: Necesidad insatisfecha de planificación familiar | C13: 0.142
A15: Alimento
B16: Fracción de agricultura de subsistencia | C16: 0.1
B17: Fracción que consume arroz como principal alimento básico | C17: 0.01
B18: Fracción que consume trigo como principal alimento básico | C18: 0.98
B19: Fracción que consume maíz como principal alimento básico | C19: 0.01
B20: Fracción de otros alimentos básicos como alimento principal | C20: =1-frac_rice-frac_wheat-frac_maize -> 0
A22: Distribución de edad de las mujeres embarazadas
B23: Porcentaje de mujeres embarazadas de 15 a 19 años | C23: 0.0393
B24: Porcentaje de mujeres embarazadas de 20 a 29 años | C24: 0.4959
B25: Porcentaje de mujeres embarazadas de 30 a 39 años | C25: 0.4202
B26: Porcentaje de mujeres embarazadas de 40 a 49 años | C26: 0.0446
A28: Espaciamiento entre los nacimientos
B29: El primer nacimiento | C29: 0.25976927
B30: menos de 18 meses | C30: 0.11570908
B31: 18-23 meses | C31: 0.098983207
B32: 24 meses o más | C32: 0.52553844
B33: Total (debe ser el 100%) | C33: =SUM(C29:C32) -> 1
A35: Mortalidad y factores de riesgo en el año de referencia
A36: Mortalidad
B37: Mortalidad neonatal (por cada 1.000 nacidos vivos) | C37: 8.53679
B38: Mortalidad infantil (por cada 1.000 nacidos vivos) | C38: 12.56445
B39: Mortalidad de menores de 5 años (por cada 1.000 nacidos vivos) | C39: 14.59897
B40: Mortalidad materna (por cada 1.000 nacidos vivos) | C40: 0.41
B41: Fracción de embarazos que terminan en aborto espontáneo | C41: 0.12
B42: Nacidos muertos (por cada 1.000 nacimientos totales) | C42: 8.9988
A44: Distribución del desenlace del nacimiento
B45: Prematuro PEG (pequeño para la edad gestacional) | C45: 0.0073871
B46: Prematuro AEG (adecuado para edad gestacional) | C46: 0.0793735
B47: Nacido a término PEG (pequeño para la edad gestacional) | C47: 0.0739759
B48: Nacido a término AEG (Adecuado para la edad gestacional) | C48: 0.4684155
A50: Incidencia de la diarrea
B51: Promedio de episodios por año: <1 mes | C51: 3.692
B52: Promedio de episodios por año: 1-5 meses | C52: 3.692
B53: Promedio de episodios por año: 6-11 meses | C53: 5.148
B54: Promedio de episodios por año: 12-23 meses | C54: 3.38
B55: Promedio de episodios por año: 24-59 meses | C55: 1.6033333
A57: Otros riesgos
B58: Porcentaje de diarrea grave | C58: 0.020689655
B59: Porcentaje de anemia que es deficiente en hierro | C59: 0.603368
B60: Prevalencia de preeclampsia | C60: 0.046
B61: Prevalencia de eclampsia | C61: 0.014
B62: Bajo peso al nacer | C62: 0.18936664

Sheet Proyecciones demográficas
A1: año | B1: Número de nacimientos | C1: WRA: 15-19 años (mujeres en edad reproductiva) | D1: WRA: 20-29 años (mujeres en edad reproductiva) | E1: WRA: 30-39 años (mujeres en edad reproductiva) | F1: WRA: 40-49 años (mujeres en edad reproductiva) | G1: Total mujeres en edad reproductiva | H1: Estimación de mujeres embarazadas | I1: mujeres en edad reproductiva no embarazadas
A2: =start_year -> 2024 | B2: 240649 | C2: 679306.5 | D2: 951608.5 | E2: 797901 | F2: 547213.5 | G2: =C2+D2+E2+F2 -> 2976029.5 | H2: =(B2 + stillbirth*B2/(1000-stillbirth))/(1-abortion) -> 275947.97 | I2: =G2-H2 -> 2700081.5
A3: =IF($A$2+ROW(A3)-2<=end_year,A2+1,"") -> 2025 | B3: 238928 | C3: 686095 | D3: 950437 | E3: 808551.5 | F3: 555412 | G3: =C3+D3+E3+F3 -> 3000495.5 | H3: =(B3 + stillbirth*B3/(1000-stillbirth))/(1-abortion) -> 273974.53 | I3: =G3-H3 -> 2726521
A4: =IF($A$2+ROW(A4)-2<=end_year,A3+1,"") -> 2026 | B4: 237233 | C4: 688055.5 | D4: 952215 | E4: 819695.5 | F4: 564534 | G4: =C4+D4+E4+F4 -> 3024500 | H4: =(B4 + stillbirth*B4/(1000-stillbirth))/(1-abortion) -> 272030.91 | I4: =G4-H4 -> 2752469.1
A5: =IF($A$2+ROW(A5)-2<=end_year,A4+1,"") -> 2027 | B5: 236558 | C5: 683644 | D5: 961047 | E5: 830106 | F5: 574448 | G5: =C5+D5+E5+F5 -> 3049245 | H5: =(B5 + stillbirth*B5/(1000-stillbirth))/(1-abortion) -> 271256.9 | I5: =G5-H5 -> 2777988.1
A6: =IF($A$2+ROW(A6)-2<=end_year,A5+1,"") -> 2028 | B6: 235368 | C6: 675667 | D6: 976894.5 | E6: 838610 | F6: 584665.5 | G6: =C6+D6+E6+F6 -> 3075837 | H6: =(B6 + stillbirth*B6/(1000-stillbirth))/(1-abortion) -> 269892.34 | I6: =G6-H6 -> 2805944.7
A7: =IF($A$2+ROW(A7)-2<=end_year,A6+1,"") -> 2029 | B7: 234379 | C7: 666779 | D7: 995451 | E7: 845529 | F7: 595286.5 | G7: =C7+D7+E7+F7 -> 3103045.5 | H7: =(B7 + stillbirth*B7/(1000-stillbirth))/(1-abortion) -> 268758.27 | I7: =G7-H7 -> 2834287.2
A8: =IF($A$2+ROW(A8)-2<=end_year,A7+1,"") -> 2030 | B8: 233757 | C8: 654020.5 | D8: 1014542.5 | E8: 853667 | F8: 605926.5 | G8: =C8+D8+E8+F8 -> 3128156.5 | H8: =(B8 + stillbirth*B8/(1000-stillbirth))/(1-abortion) -> 268045.04 | I8: =G8-H8 -> 2860111.5
A9: =IF($A$2+ROW(A9)-2<=end_year,A8+1,"") -> 2031 | B9: 234204 | C9: 642187 | D9: 1032232.5 | E9: 862297 | F9: 616712.5 | G9: =C9+D9+E9+F9 -> 3153429 | H9: =(B9 + stillbirth*B9/(1000-stillbirth))/(1-abortion) -> 268557.61 | I9: =G9-H9 -> 2884871.4
A10: =IF($A$2+ROW(A10)-2<=end_year,A9+1,"") -> 2032 | B10: 234312 | C10: 634732 | D10: 1047673.5 | E10: 868908 | F10: 628340.5 | G10: =C10+D10+E10+F10 -> 3179654 | H10: =(B10 + stillbirth*B10/(1000-stillbirth))/(1-abortion) -> 268681.45 | I10: =G10-H10 -> 2910972.6
A11: =IF($A$2+ROW(A11)-2<=end_year,A10+1,"") -> 2033 | B11: 233299 | C11: 630192 | D11: 1058977 | E11: 876107 | F11: 641512.5 | G11: =C11+D11+E11+F11 -> 3206788.5 | H11: =(B11 + stillbirth*B11/(1000-stillbirth))/(1-abortion) -> 267519.86 | I11: =G11-H11 -> 2939268.6
A12: =IF($A$2+ROW(A12)-2<=end_year,A11+1,"") -> 2034 | B12: 233866 | C12: 625752 | D12: 1068994.5 | E12: 884124 | F12: 656681.5 | G12: =C12+D12+E12+F12 -> 3235552 | H12: =(B12 + stillbirth*B12/(1000-stillbirth))/(1-abortion) -> 268170.03 | I12: =G12-H12 -> 2967382
A13: =IF($A$2+ROW(A13)-2<=end_year,A12+1,"") -> 2035 | B13: 234573 | C13: 623224.5 | D13: 1076718.5 | E13: 892856 | F13: 673273 | G13: =C13+D13+E13+F13 -> 3266072 | H13: =(B13 + stillbirth*B13/(1000-stillbirth))/(1-abortion) -> 268980.73 | I13: =G13-H13 -> 2997091.3
A14: =IF($A$2+ROW(A14)-2<=end_year,A13+1,"")
A15: =IF($A$2+ROW(A15)-2<=end_year,A14+1,"")
A16: =IF($A$2+ROW(A16)-2<=end_year,A15+1,"")
A17: =IF($A$2+ROW(A17)-2<=end_year,A16+1,"")
A18: =IF($A$2+ROW(A18)-2<=end_year,A17+1,"")
A19: =IF($A$2+ROW(A19)-2<=end_year,A18+1,"")
A20: =IF($A$2+ROW(A20)-2<=end_year,A19+1,"")
A21: =IF($A$2+ROW(A21)-2<=end_year,A20+1,"")
A22: =IF($A$2+ROW(A22)-2<=end_year,A21+1,"")
A23: =IF($A$2+ROW(A23)-2<=end_year,A22+1,"")
A24: =IF($A$2+ROW(A24)-2<=end_year,A23+1,"")
A25: =IF($A$2+ROW(A25)-2<=end_year,A24+1,"")
... A37: =IF($A$2+ROW(A37)-2<=end_year,A36+1,"")
A38: =IF($A$2+ROW(A38)-2<=end_year,A37+1,"") | G38: =C38+D38+E38+F38 -> 0 | H38: =(B38 + stillbirth*B38/(1000-stillbirth))/(1-abortion) -> 0 | I38: =G38-H38 -> 0
A39: =IF($A$2+ROW(A39)-2<=end_year,A38+1,"") | G39: =C39+D39+E39+F39 -> 0 | H39: =(B39 + stillbirth*B39/(1000-stillbirth))/(1-abortion) -> 0 | I39: =G39-H39 -> 0
A40: =IF($A$2+ROW(A40)-2<=end_year,A39+1,"") | G40: =C40+D40+E40+F40 -> 0 | H40: =(B40 + stillbirth*B40/(1000-stillbirth))/(1-abortion) -> 0 | I40: =G40-H40 -> 0

Sheet Causas de muerte
A1: ="Porcentaje de muertes en el año de referencia ("&start_year&") atribuible a la causa" -> Porcentaje de muertes en el año de referencia (2024) atribuible a la causa
A2: Neonatal | B2: Causas | C2: <1 mes
B3: Diarrea neonatal | C3: 0
B4: Sepsis neonatal | C4: 0.0727346
B5: Neumonía neonatal | C5: 0.0297556
B6: Asfixia neonatal | C6: 0.1467637
B7: Prematuridad neonatal | C7: 0.412501
B8: Tétanos neonatal | C8: 0.0061284
B9: Anomalías congénitas neonatales | C9: 0.2188107
B10: Neonatal otros | C10: 0.113306
B11: Total (debe ser el 100%) | C11: =SUM(C3:C10) -> 1
A13: Niños | B13: Causas | C13: 1-5 meses | D13: 6-11 meses | E13: 12-23 meses | F13: 24-59 meses
B14: Diarrea | C14: 0.017752015 | D14: 0.017752015 | E14: 0.017752015 | F14: 0.017752015
B15: Neumonía | C15: 0.61124028 | D15: 0.61124028 | E15: 0.61124028 | F15: 0.61124028
B16: Meningitis | C16: 0.016022347 | D16: 0.016022347 | E16: 0.016022347 | F16: 0.016022347
B17: Sarampión | C17: 0.0058457814 | D17: 0.0058457814 | E17: 0.0058457814 | F17: 0.0058457814
B18: Malaria | C18: 0 | D18: 0 | E18: 0 | F18: 0
B19: Tosferina | C19: 0.02222924 | D19: 0.02222924 | E19: 0.02222924 | F19: 0.02222924
B20: SIDA | C20: 0.0049781085 | D20: 0.0049781085 | E20: 0.0049781085 | F20: 0.0049781085
B21: Lesión | C21: 0.26469793 | D21: 0.26469793 | E21: 0.26469793 | F21: 0.26469793
B22: Otro | C22: 0.057234305 | D22: 0.057234305 | E22: 0.057234305 | F22: 0.057234305
B23: Total (debe ser el 100%) | C23: =SUM(C14:C22) -> 1 | D23: =SUM(D14:D22) -> 1 | E23: =SUM(E14:E22) -> 1 | F23: =SUM(F14:F22) -> 1
A25: Mujeres embarazadas | B25: Causas | C25: Mujeres embarazadas
B26: Hemorragia pre-parto | C26: 0.10922641
B27: Hemorragia intraparto | C27: 0.017615204
B28: Hemorragia posparto | C28: 0.035403469
B29: Trastornos hipertensivos | C29: 0.081855017
B30: Sepsis | C30: 0.067261675
B31: Aborto | C31: 0.028928879
B32: Embolia | C32: 0.23338838
B33: Otras causas directas | C33: 0.13208631
B34: Causas indirectas | C34: 0.29423466
B35: Total (debe ser el 100%) | C35: =SUM(C26:C34) -> 1

Sheet Distribución estado nutricional
A1: ="Porcentaje de población en cada categoría en el año de referencia ("&start_year&")" -> Porcentaje de población en cada categoría en el año de referencia (2024) | B1: Estado | C1: <1 mes | D1: 1-5 meses | E1: 6-11 meses | F1: 12-23 meses | G1: 24-59 meses
A2: Retraso en el crecimiento (Talla para la edad) | B2: Normal (score HAZ > -1) | C2: =IFERROR(1-_xlfn.NORM.DIST(_xlfn.NORM.INV(SUM(C4:C5), 0, 1) + 1, 0, 1, TRUE), "") -> 0.63376885 | D2: =IFERROR(1-_xlfn.NORM.DIST(_xlfn.NORM.INV(SUM(D4:D5), 0, 1) + 1, 0, 1, TRUE), "") -> 0.63376885 | E2: =IFERROR(1-_xlfn.NORM.DIST(_xlfn.NORM.INV(SUM(E4:E5), 0, 1) + 1, 0, 1, TRUE), "") -> 0.66632415 | F2: =IFERROR(1-_xlfn.NORM.DIST(_xlfn.NORM.INV(SUM(F4:F5), 0, 1) + 1, 0, 1, TRUE), "") -> 0.59653399 | G2: =IFERROR(1-_xlfn.NORM.DIST(_xlfn.NORM.INV(SUM(G4:G5), 0, 1) + 1, 0, 1, TRUE), "") -> 0.69260682
B3: Leve (score HAZ entre -2 y -1) | C3: =IFERROR(_xlfn.NORM.DIST(_xlfn.NORM.INV(SUM(C4:C5), 0, 1) + 1, 0, 1, TRUE) - SUM(C4:C5), "") -> 0.27640915 | D3: =IFERROR(_xlfn.NORM.DIST(_xlfn.NORM.INV(SUM(D4:D5), 0, 1) + 1, 0, 1, TRUE) - SUM(D4:D5), "") -> 0.27640915 | E3: =IFERROR(_xlfn.NORM.DIST(_xlfn.NORM.INV(SUM(E4:E5), 0, 1) + 1, 0, 1, TRUE) - SUM(E4:E5), "") -> 0.25728655 | F3: =IFERROR(_xlfn.NORM.DIST(_xlfn.NORM.INV(SUM(F4:F5), 0, 1) + 1, 0, 1, TRUE) - SUM(F4:F5), "") -> 0.29678721 | G3: =IFERROR(_xlfn.NORM.DIST(_xlfn.NORM.INV(SUM(G4:G5), 0, 1) + 1, 0, 1, TRUE) - SUM(G4:G5), "") -> 0.24100628
B4: Moderado (score HAZ entre -3 y -2) | C4: 0.0715416 | D4: 0.0715416 | E4: 0.0726949 | F4: 0.0814739 | G4: 0.0528273
B5: Alto (puntuación HAZ < -3) | C5: 0.0182804 | D5: 0.0182804 | E5: 0.0036944 | F5: 0.0252049 | G5: 0.0135596
A8: Emaciación (peso para la talla) | B8: Normal (score WHZ > -1) | C8: =IFERROR(1-_xlfn.NORM.DIST(_xlfn.NORM.INV(SUM(C10:C11), 0, 1) + 1, 0, 1, TRUE), "") -> 0.7376968 | D8: =IFERROR(1-_xlfn.NORM.DIST(_xlfn.NORM.INV(SUM(D10:D11), 0, 1) + 1, 0, 1, TRUE), "") -> 0.7376968 | E8: =IFERROR(1-_xlfn.NORM.DIST(_xlfn.NORM.INV(SUM(E10:E11), 0, 1) + 1, 0, 1, TRUE), "") -> 0.85235132 | F8: =IFERROR(1-_xlfn.NORM.DIST(_xlfn.NORM.INV(SUM(F10:F11), 0, 1) + 1, 0, 1, TRUE), "") -> 0.86275873 | G8: =IFERROR(1-_xlfn.NORM.DIST(_xlfn.NORM.INV(SUM(G10:G11), 0, 1) + 1, 0, 1, TRUE), "") -> 0.83915207
B9: Leve (score WHZ entre -2 y -1) | C9: =IFERROR(_xlfn.NORM.DIST(_xlfn.NORM.INV(SUM(C10:C11), 0, 1) + 1, 0, 1, TRUE) - SUM(C10:C11), "") -> 0.2114107 | D9: =IFERROR(_xlfn.NORM.DIST(_xlfn.NORM.INV(SUM(D10:D11), 0, 1) + 1, 0, 1, TRUE) - SUM(D10:D11), "") -> 0.2114107 | E9: =IFERROR(_xlfn.NORM.DIST(_xlfn.NORM.INV(SUM(E10:E11), 0, 1) + 1, 0, 1, TRUE) - SUM(E10:E11), "") -> 0.12729858 | F9: =IFERROR(_xlfn.NORM.DIST(_xlfn.NORM.INV(SUM(F10:F11), 0, 1) + 1, 0, 1, TRUE) - SUM(F10:F11), "") -> 0.11905767 | G9: =IFERROR(_xlfn.NORM.DIST(_xlfn.NORM.INV(SUM(G10:G11), 0, 1) + 1, 0, 1, TRUE) - SUM(G10:G11), "") -> 0.13760633
B10: MAM (puntuación WHZ entre -3 y -2) | C10: 0.0269803 | D10: 0.0269803 | E10: 0.0105953 | F10: 0.0122074 | G10: 0.0192801
B11: MAS (score WHZ < -3) | C11: 0.0239122 | D11: 0.0239122 | E11: 0.0097548 | F11: 0.0059762 | G11: 0.0039615
A13: Anemia | C13: <1 mes | D13: 1-5 meses | E13: 6-11 meses | F13: 12-23 meses | G13: 24-59 meses | H13: PW: 15-19 años | I13: PW: 20-29 años | J13: PW: 30-39 años | K13: PW: 40-49 años | L13: WRA: 15-19 años (mujeres en edad reproductiva) | M13: WRA: 20-29 años (mujeres en edad reproductiva) | N13: WRA: 30-39 años (mujeres en edad reproductiva) | O13: WRA: 40-49 años (mujeres en edad reproductiva)
B14: Prevalencia de anemia | C14: 0.5899667 | D14: 0.58808578 | E14: 0.58808578 | F14: 0.29456096 | G14: 0.29456096 | H14: 0.371 | I14: 0.371 | J14: 0.371 | K14: 0.371 | L14: 0.345 | M14: 0.345 | N14: 0.345 | O14: 0.345
B15: Prevalencia de anemia por deficiencia de hierro | C15: =iron_deficiency_anaemia*C14 -> 0.35596703 | D15: =iron_deficiency_anaemia*D14 -> 0.35483214 | E15: =iron_deficiency_anaemia*E14 -> 0.35483214 | F15: =iron_deficiency_anaemia*F14 -> 0.17772866 | G15: =iron_deficiency_anaemia*G14 -> 0.17772866 | H15: =iron_deficiency_anaemia*H14 -> 0.22384953 | I15: =iron_deficiency_anaemia*I14 -> 0.22384953 | J15: =iron_deficiency_anaemia*J14 -> 0.22384953 | ... O15: =iron_deficiency_anaemia*O14 -> 0.20816196

Sheet Distribución de lactancia
A1: ="Porcentaje de niños en cada categoría en el año de referencia ("&start_year&")" -> Porcentaje de niños en cada categoría en el año de referencia (2024) | B1: Estado | C1: <1 mes | D1: 1-5 meses | E1: 6-11 meses | F1: 12-23 meses | G1: 24-59 meses
A2: Lactancia materna | B2: Exclusivo | C2: 0.4275603 | D2: 0.2062329 | E2: 0 | F2: 0 | G2: 0
B3: Predominante | C3: 0.1007744 | D3: 0.1128769 | E3: 0 | F3: 0 | G3: 0
B4: Parcial | C4: 0.3694653 | D4: 0.4636665 | E4: 0.5461004 | F4: 0.2614762 | G4: 0
B5: Ninguno | C5: =1-SUM(C2:C4) -> 0.1022 | D5: =1-SUM(D2:D4) -> 0.2172237 | E5: =1-SUM(E2:E4) -> 0.4538996 | F5: =1-SUM(F2:F4) -> 0.7385238 | G5: =1-SUM(G2:G4) -> 1

Sheet Tendencias temporales
A1: Riesgo | B1: Población | C1: 2010 | D1: 2011 | E1: 2012 | F1: 2013 | G1: 2014 | H1: 2015 | I1: 2016 | J1: 2017 | K1: 2018
A2: Prevalencia del retraso del crecimiento (%) | B2: Niños de 0 a 59 meses
A4: Prevalencia de emaciación (%) | B4: Niños de 0 a 59 meses
A6: Prevalencia de anemia (%) | B6: Niños de 0 a 59 meses
B7: Mujeres embarazadas
B8: Mujeres en edad reproductiva
A10: Prevalencia de lactancia materna adecuada para la edad | B10: Niños de 0 a 5 meses
B11: Niños de 6 a 23 meses
A13: Mortalidad | B13: Menores de cinco años (muertes por cada 1.000 nacimientos)
B14: Materna (muertes por cada 1.000 nacimientos)

Sheet Variables económicas 
A1: Parameter | B1: Value
A2: PIB per cápita | B2: 4311
A3: Crecimiento anual del PIB | B3: 0.03
A4: Participación del trabajo en el PIB | B4: 0.43899
A5: Descuento temporal (costos) | B5: 0.03
A6: Descuento temporal (beneficios) | B6: 0.03
A7: Edad de inicio de la productividad laboral | B7: 18
A8: Edad a la que se acaba la productividad laboral | B8: 65
A9: Participación laboral femenina | B9: 0.14511
A10: Porcentaje de ingresos vitales que realmente se han ganado | B10: 0.9
A11: Reducción total de ingresos vitales en individuos con retraso del crecimiento | B11: 0.66
A12: Disminución de productividad debido a la anemia infantil (%) | B12: 0.025
A13: Disminución de productividad debido al bajo peso al nacer (%) | B13: 0.075
... A18: Porcentaje de mortinatos a incluir en la pérdida de productividad | B18: 0
A21: Life tables | B21: Age 5 | C21: Age 10 | D21: Age 15 | E21: Age 20 | F21: Age 25 | G21: Age 30 | H21: Age 35 | I21: Age 40 | J21: Age 45 | K21: Age 50 | L21: Age 55 | M21: Age 60 | N21: Age 65 | O21: Age 70
A22: Número de personas vivas restantes (empezando con 100.000 nacimientos) | B22: 98375.219 | C22: 98201.371 | D22: 98038.989 | E22: 97865.114 | F22: 97649.534 | G22: 97408.892 | H22: 97107.769 | I22: 96710.643 | J22: 96111.343 | K22: 95137.663 | L22: 93522.521 | M22: 90922.55 | N22: 86532.694 | O22: 79309.165

Sheet Paquetes de IYCF
A1: Paquete alimentación del lactante y del niño pequeño (IYCF) | B1: Población objetivo | C1: Centro de salud | D1: Comunidad | E1: Medios de comunicación masivos
A2: IYCF 1-alimentación del lactante y del niño pequeño | B2: Mujeres embarazadas | E2: =IF(E$7="","",E$7)
B3: <1 mes | D3: x | E3: =IF(E$7="","",E$7)
B4: 1-5 meses | D4: x | E4: =IF(E$7="","",E$7)
B5: 6-11 meses | D5: x | E5: =IF(E$7="","",E$7)
B6: 12-23 meses | D6: x | E6: =IF(E$7="","",E$7)
B7: Todo
A9: IYCF 2-alimentación del lactante y del niño pequeño | B9: Mujeres embarazadas | E9: =IF(E$7="","",E$7)
B10: <1 mes | E10: =IF(E$7="","",E$7)
B11: 1-5 meses | E11: =IF(E$7="","",E$7)
B12: 6-11 meses | D12: x | E12: =IF(E$7="","",E$7)
B13: 12-23 meses | D13: x | E13: =IF(E$7="","",E$7)
B14: Todo
A16: IYCF 3-alimentación del lactante y del niño pequeño | B16: Mujeres embarazadas | D16: x | E16: =IF(E$7="","",E$7)
B17: <1 mes | D17: x | E17: =IF(E$7="","",E$7)
B18: 1-5 meses | D18: x | E18: =IF(E$7="","",E$7)
B19: 6-11 meses | D19: x | E19: =IF(E$7="","",E$7)
B20: 12-23 meses | D20: x | E20: =IF(E$7="","",E$7)
B21: Todo

Sheet Tratamiento de la MAS
A1: Field | B1: Por defecto | C1: Extensión | D1: Añadir extensión
A2: Programa | B2: Tratamiento de la MAS | C2: Manejo de la Malnutrición Aguda Moderada (MAM)
A3: Método de entrega | B3: Centro de salud | C3: Basado en la comunidad

Sheet Costo y cobertura del programa
A1: Programa | B1: ="Cobertura de referencia ("&start_year&")" -> Cobertura de referencia (2024) | C1: Cobertura de saturación de la población objetivo | D1: Costo unitario (US$) | E1: Relación costo-cobertura | F1: Aumento máximo anual | G1: Disminución máxima anual
A2: Suplemento energético-proteico equilibrado | B2: 0 | C2: 0.95 | D2: 19.75 | E2: Lineal (costo marginal constante) [por defecto] | F2: 1 | G2: 1
A3: Suplemento con calcio | B3: 0 | C3: 0.95 | D3: 19.75 | E3: Lineal (costo marginal constante) [por defecto] | F3: 1 | G3: 1
A4: Transferencias de efectivo | B4: 0 | C4: 0.95 | D4: 7.4289689 | E4: Lineal (costo marginal constante) [por defecto] | F4: 1 | G4: 1
A5: Retraso en el pinzamiento del cordón umbilical | B5: 0 | C5: 0.95 | D5: 0.48 | E5: Lineal (costo marginal constante) [por defecto] | F5: 1 | G5: 1
A6: Planificación familiar | B6: 0 | C6: 0.95 | D6: 99.99 | E6: Lineal (costo marginal constante) [por defecto] | F6: 1 | G6: 1
A7: Enriquecimiento del maíz con hierro y ácido fólico | B7: 0 | C7: 0.95 | D7: 0.19283527 | E7: Lineal (costo marginal constante) [por defecto] | F7: 1 | G7: 1
A8: Enriquecimiento del arroz con hierro y ácido fólico | B8: 0 | C8: 0.95 | D8: 0.10284548 | E8: Lineal (costo marginal constante) [por defecto] | F8: 1 | G8: 1
A9: Enriquecimiento de la harina de trigo con hierro y ácido fólico | B9: 0.5 | C9: 0.95 | D9: 0.4 | E9: Lineal (costo marginal constante) [por defecto] | F9: 1 | G9: 1
A10: Suplementación con hierro y ácido fólico (comunidad) | B10: 0.4891141 | C10: 0.95 | D10: 13.004412 | E10: Lineal (costo marginal constante) [por defecto] | F10: 1 | G10: 1
A11: Suplementación con hierro y ácido fólico (centro de salud) | B11: 0 | C11: 0.95 | D11: 13.004412 | E11: Lineal (costo marginal constante) [por defecto] | F11: 1 | G11: 1
A12: Suplementación con hierro y ácido fólico (minorista) | B12: 0 | C12: 0.95 | D12: 13.004412 | E12: Lineal (costo marginal constante) [por defecto] | F12: 1 | G12: 1
A13: Suplementación con hierro y ácido fólico (escuela) | B13: 0 | C13: 0.95 | D13: 13.004412 | E13: Lineal (costo marginal constante) [por defecto] | F13: 1 | G13: 1
... A39: Suplementación con zinc | B39: 0 | C39: 0.95 | D39: 3.43 | E39: Lineal (costo marginal constante) [por defecto] | F39: 1 | G39: 1

Sheet Dependencias del programa
A1: Programa | B1: Exclusión de intervención dependiente | C1: Dependencia de otra intervención
A2: Suplementación con hierro y ácido fólico para mujeres embarazadas (comunidad) | B2: Suplementación con micronutrientes múltiples
A3: Suplementación con hierro y ácido fólico para mujeres embarazadas (centro de salud) | B3: Suplementación con micronutrientes múltiples
A4: Suministro público de alimentos complementarios | B4: Suplementos nutricionales a base de lípidos
A5: Suministro público de alimentos complementarios | B5: Suplementos nutricionales a base de lípidos en pequeñas cantidades
A6: Micronutrientes en polvo | B6: Suplementos nutricionales a base de lípidos en pequeñas cantidades
A7: Suplementación con zinc | B7: Suplementos nutricionales a base de lípidos en pequeñas cantidades

Sheet Programas de referencia
A1: Programa
A2: Planificación familiar
A3: IPTp-Tratamiento preventivo intermitente de la malaria en el embarazo
A4: Mosquiteros tratados con insecticida de larga duración
A5: WASH: Lavado de manos
A6: WASH: Eliminación higiénica de residuos
A7: WASH: Mejora del saneamiento
A8: WASH: Mejora de la fuente de agua
A9: WASH: Agua corriente o entubada
A10: Tratamiento de la MAS

Sheet Incidencia de las afecciones
A1: Condición | B1: <1 mes | C1: 1-5 meses | D1: 6-11 meses | E1: 12-23 meses | F1: 24-59 meses
A2: Diarrea | B2: ='Entradas de población-año base'!C51 -> 3.692 | C2: ='Entradas de población-año base'!C52 -> 3.692 | D2: ='Entradas de población-año base'!C53 -> 5.148 | E2: ='Entradas de población-año base'!C54 -> 3.38 | F2: ='Entradas de población-año base'!C55 -> 1.6033333
A3: MAM | B3: =frac_mam_1month * 2.6 -> 0.07014878 | C3: =frac_mam_1_5months * 2.6 -> 0.07014878 | D3: =frac_mam_6_11months * 2.6 -> 0.02754778 | E3: =frac_mam_12_23months * 2.6 -> 0.03173924 | F3: =frac_mam_24_59months * 2.6 -> 0.05012826
A4: MAS | B4: =frac_sam_1month * 2.6 -> 0.06217172 | C4: =frac_sam_1_5months * 2.6 -> 0.06217172 | D4: =frac_sam_6_11months * 2.6 -> 0.02536248 | E4: =frac_sam_12_23months * 2.6 -> 0.01553812 | F4: =frac_sam_24_59months * 2.6 -> 0.0102999

Sheet Población objetivo del programa
A1: Amplio grupo de población | B1: Programa | C1: <1 mes | D1: 1-5 meses | E1: 6-11 meses | F1: 12-23 meses | G1: 24-59 meses | H1: PW: 15-19 años | I1: PW: 20-29 años | J1: PW: 30-39 años | K1: PW: 40-49 años | L1: WRA: 15-19 años (mujeres en edad reproductiva) | M1: WRA: 20-29 años (mujeres en edad reproductiva) | N1: WRA: 30-39 años (mujeres en edad reproductiva) | O1: WRA: 40-49 años (mujeres en edad reproductiva)
A2: Niños | B2: Transferencias de efectivo | C2: 0 | D2: 0 | E2: =food_insecure -> 0.157 | F2: =food_insecure -> 0.157 | G2: 0 | H2: 0 | I2: 0 | J2: 0 | K2: 0 | L2: 0 | M2: 0 | N2: 0 | O2: 0
B3: Retraso en el pinzamiento del cordón umbilical | C3: 1 | D3: 0 | E3: 0 | F3: 0 | G3: 0 | H3: 0 | I3: 0 | J3: 0 | K3: 0 | L3: 0 | M3: 0 | N3: 0 | O3: 0
B4: Método de la madre canguro | C4: 1 | D4: 0 | E4: 0 | F4: 0 | G4: 0 | H4: 0 | I4: 0 | J4: 0 | K4: 0 | L4: 0 | M4: 0 | N4: 0 | O4: 0
B5: Suplementos nutricionales a base de lípidos | C5: 0 | D5: 0 | E5: =food_insecure -> 0.157 | F5: =food_insecure -> 0.157 | G5: 0 | H5: 0 | I5: 0 | J5: 0 | K5: 0 | L5: 0 | M5: 0 | N5: 0 | O5: 0
B6: Micronutrientes en polvo | C6: 0 | D6: 0 | E6: =1 -> 1 | F6: =1 -> 1 | G6: =1 -> 1 | H6: 0 | I6: 0 | J6: 0 | K6: 0 | L6: 0 | M6: 0 | N6: 0 | O6: 0
B7: Sales de rehidratación oral | C7: =diarrhoea_1mo*frac_diarrhea_severe -> 0.076386207 | D7: =diarrhoea_1_5mo*frac_diarrhea_severe -> 0.076386207 | E7: =diarrhoea_6_11mo*frac_diarrhea_severe -> 0.10651034 | F7: =diarrhoea_12_23mo*frac_diarrhea_severe -> 0.069931034 | G7: =diarrhoea_24_59mo*frac_diarrhea_severe -> 0.033172414 | H7: 0 | I7: 0 | J7: 0 | K7: 0 | L7: 0 | M7: 0 | N7: 0 | O7: 0
B8: Suministro público de alimentos complementarios | C8: 0 | D8: 0 | E8: =food_insecure -> 0.157 | F8: =food_insecure -> 0.157 | G8: 0 | H8: 0 | I8: 0 | J8: 0 | K8: 0 | L8: 0 | M8: 0 | N8: 0 | O8: 0
B9: Suplementos nutricionales a base de lípidos en pequeñas cantidades | C9: 0 | D9: 0 | E9: =food_insecure -> 0.157 | F9: =food_insecure -> 0.157 | G9: 0 | H9: 0 | I9: 0 | J9: 0 | K9: 0 | L9: 0 | M9: 0 | N9: 0 | O9: 0
B10: Tratamiento de la MAS | C10: 0 | D10: =IF(ISBLANK(comm_deliv), frac_children_health_facility,1) -> 1 | E10: =IF(ISBLANK(comm_deliv), frac_children_health_facility,1) -> 1 | F10: =IF(ISBLANK(comm_deliv), frac_children_health_facility,1) -> 1 | G10: =IF(ISBLANK(comm_deliv), frac_children_health_facility,1) -> 1 | H10: 0 | I10: 0 | J10: 0 | K10: 0 | L10: 0 | M10: 0 | N10: 0 | O10: 0
B11: Suplementación con vitamina A | C11: 0 | D11: 0 | E11: 1 | F11: 1 | G11: 1 | H11: 0 | I11: 0 | J11: 0 | K11: 0 | L11: 0 | M11: 0 | N11: 0 | O11: 0
B12: Zinc para el tratamiento + SRO | C12: =diarrhoea_1mo*frac_diarrhea_severe -> 0.076386207 | D12: =diarrhoea_1_5mo*frac_diarrhea_severe -> 0.076386207 | E12: =diarrhoea_6_11mo*frac_diarrhea_severe -> 0.10651034 | F12: =diarrhoea_12_23mo*frac_diarrhea_severe -> 0.069931034 | G12: =diarrhoea_24_59mo*frac_diarrhea_severe -> 0.033172414 | H12: 0 | I12: 0 | J12: 0 | K12: 0 | L12: 0 | M12: 0 | N12: 0 | O12: 0
B13: Suplementación con zinc | C13: 0 | D13: 0 | E13: 1 | F13: 1 | G13: 1 | H13: 0 | I13: 0 | J13: 0 | K13: 0 | L13: 0 | M13: 0 | N13: 0 | O13: 0
A15: Mujeres embarazadas | B15: Suplemento energético-proteico equilibrado | C15: 0 | D15: 0 | E15: 0 | F15: 0 | G15: 0 | H15: =food_insecure -> 0.157 | I15: =food_insecure -> 0.157 | J15: =food_insecure -> 0.157 | K15: =food_insecure -> 0.157 | L15: 0 | M15: 0 | N15: 0 | O15: 0
B16: Suplemento con calcio | C16: 0 | D16: 0 | E16: 0 | F16: 0 | G16: 0 | H16: =food_insecure -> 0.157 | I16: =food_insecure -> 0.157 | J16: =food_insecure -> 0.157 | K16: =food_insecure -> 0.157 | L16: 0 | M16: 0 | N16: 0 | O16: 0
B17: Suplementación con hierro y ácido fólico para mujeres embarazadas (comunidad) | C17: 0 | D17: 0 | E17: 0 | F17: 0 | G17: 0 | H17: =1 -> 1 | I17: =1 -> 1 | J17: =1 -> 1 | K17: =1 -> 1 | L17: 0 | M17: 0 | N17: 0 | O17: 0
B18: Suplementación con hierro y ácido fólico para mujeres embarazadas (centro de salud) | C18: 0 | D18: 0 | E18: 0 | F18: 0 | G18: 0 | H18: =frac_PW_health_facility -> 1 | I18: =frac_PW_health_facility -> 1 | J18: =frac_PW_health_facility -> 1 | K18: =frac_PW_health_facility -> 1 | L18: 0 | M18: 0 | N18: 0 | O18: 0
B19: IPTp-Tratamiento preventivo intermitente de la malaria en el embarazo | C19: 0 | D19: 0 | E19: 0 | F19: 0 | G19: 0 | H19: =frac_malaria_risk -> 0.01 | I19: =frac_malaria_risk -> 0.01 | J19: =frac_malaria_risk -> 0.01 | K19: =frac_malaria_risk -> 0.01 | L19: 0 | M19: 0 | N19: 0 | O19: 0
B20: Magnesio para la eclampsia | C20: 0 | D20: 0 | E20: 0 | F20: 0 | G20: 0 | H20: 1 | I20: 1 | J20: 1 | K20: 1 | L20: 0 | M20: 0 | N20: 0 | O20: 0
B21: Magnesio para la preeclampsia | C21: 0 | D21: 0 | E21: 0 | F21: 0 | G21: 0 | H21: 1 | I21: 1 | J21: 1 | K21: 1 | L21: 0 | M21: 0 | N21: 0 | O21: 0
B22: Suplementación con micronutrientes múltiples | C22: 0 | D22: 0 | E22: 0 | F22: 0 | G22: 0 | H22: =1 -> 1 | I22: =1 -> 1 | J22: =1 -> 1 | K22: =1 -> 1 | L22: 0 | M22: 0 | N22: 0 | O22: 0
A24: Mujeres en edad reproductiva no embarazadas | B24: Planificación familiar | C24: 0 | D24: 0 | E24: 0 | F24: 0 | G24: 0 | H24: 0 | I24: 0 | J24: 0 | K24: 0 | L24: =famplan_unmet_need -> 0.142 | M24: =famplan_unmet_need -> 0.142 | N24: =famplan_unmet_need -> 0.142 | O24: =famplan_unmet_need -> 0.142
B25: Suplementación con hierro y ácido fólico (comunidad) | C25: 0 | D25: 0 | E25: 0 | F25: 0 | G25: 0 | H25: 0 | I25: 0 | J25: 0 | K25: 0 | L25: =(1-food_insecure)*(0.49)*(1-school_attendance) + food_insecure*(0.7)*(1-school_attendance) -> 0.19075864 | M25: =(1-food_insecure)*(0.49)+food_insecure*(0.7) -> 0.52297 | N25: =(1-food_insecure)*(0.49)+food_insecure*(0.7) -> 0.52297 | O25: =(1-food_insecure)*(0.49)+food_insecure*(0.7) -> 0.52297
B26: Suplementación con hierro y ácido fólico (centro de salud) | C26: 0 | D26: 0 | E26: 0 | F26: 0 | G26: 0 | H26: 0 | I26: 0 | J26: 0 | K26: 0 | L26: =(1-food_insecure)*(0.21)*(1-school_attendance) + food_insecure*(0.3)*(1-school_attendance) -> 0.081753704 | M26: =(1-food_insecure)*(0.21)+food_insecure*(0.3) -> 0.22413 | N26: =(1-food_insecure)*(0.21)+food_insecure*(0.3) -> 0.22413 | O26: =(1-food_insecure)*(0.21)+food_insecure*(0.3) -> 0.22413
B27: Suplementación con hierro y ácido fólico (minorista) | C27: 0 | D27: 0 | E27: 0 | F27: 0 | G27: 0 | H27: 0 | I27: 0 | J27: 0 | K27: 0 | L27: =(1-food_insecure)*(0.3)*(1-school_attendance) -> 0.092247855 | M27: =(1-food_insecure)*(0.3) -> 0.2529 | N27: =(1-food_insecure)*(0.3) -> 0.2529 | O27: =(1-food_insecure)*(0.3) -> 0.2529
B28: Suplementación con hierro y ácido fólico (escuela) | C28: 0 | D28: 0 | E28: 0 | F28: 0 | G28: 0 | H28: 0 | I28: 0 | J28: 0 | K28: 0 | L28: =(1-food_insecure)*1*school_attendance + food_insecure*1*school_attendance -> 0.6352398 | M28: 0 | N28: 0 | O28: 0
A30: Población general | B30: Enriquecimiento del maíz con hierro y ácido fólico | C30: 0 | D30: 0 | E30: =frac_maize -> 0.01 | F30: =frac_maize -> 0.01 | G30: =frac_maize -> 0.01 | H30: =frac_maize -> 0.01 | I30: =frac_maize -> 0.01 | J30: =frac_maize -> 0.01 | K30: =frac_maize -> 0.01 | L30: =frac_maize -> 0.01 | ... O30: =frac_maize -> 0.01
B31: Enriquecimiento del arroz con hierro y ácido fólico | C31: 0 | D31: 0 | E31: =frac_rice -> 0.01 | F31: =frac_rice -> 0.01 | G31: =frac_rice -> 0.01 | H31: =frac_rice -> 0.01 | I31: =frac_rice -> 0.01 | J31: =frac_rice -> 0.01 | K31: =frac_rice -> 0.01 | L31: =frac_rice -> 0.01 | ... O31: =frac_rice -> 0.01
B32: Enriquecimiento de la harina de trigo con hierro y ácido fólico | C32: 0 | D32: 0 | E32: =frac_wheat -> 0.98 | F32: =frac_wheat -> 0.98 | G32: =frac_wheat -> 0.98 | H32: =frac_wheat -> 0.98 | I32: =frac_wheat -> 0.98 | J32: =frac_wheat -> 0.98 | K32: =frac_wheat -> 0.98 | L32: =frac_wheat -> 0.98 | ... O32: =frac_wheat -> 0.98
B33: Fortificación de la sal con hierro y yodo | C33: 0 | D33: 0 | E33: 1 | F33: 1 | G33: 1 | H33: 1 | I33: 1 | J33: 1 | K33: 1 | L33: 1 | M33: 1 | N33: 1 | O33: 1
B34: Mosquiteros tratados con insecticida de larga duración | C34: =frac_malaria_risk -> 0.01 | D34: =frac_malaria_risk -> 0.01 | E34: =frac_malaria_risk -> 0.01 | F34: =frac_malaria_risk -> 0.01 | G34: =frac_malaria_risk -> 0.01 | H34: =frac_malaria_risk -> 0.01 | I34: =frac_malaria_risk -> 0.01 | J34: =frac_malaria_risk -> 0.01 | ... O34: =frac_malaria_risk -> 0.01
B35: WASH: Lavado de manos | C35: 1 | D35: 1 | E35: 1 | F35: 1 | G35: 1 | H35: 1 | I35: 1 | J35: 1 | K35: 1 | L35: 1 | M35: 1 | N35: 1 | O35: 1
B36: WASH: Eliminación higiénica de residuos | C36: 1 | D36: 1 | E36: 1 | F36: 1 | G36: 1 | H36: 1 | I36: 1 | J36: 1 | K36: 1 | L36: 1 | M36: 1 | N36: 1 | O36: 1
B37: WASH: Mejora del saneamiento | C37: 1 | D37: 1 | E37: 1 | F37: 1 | G37: 1 | H37: 1 | I37: 1 | J37: 1 | K37: 1 | L37: 1 | M37: 1 | N37: 1 | O37: 1
B38: WASH: Mejora de la fuente de agua | C38: 1 | D38: 1 | E38: 1 | F38: 1 | G38: 1 | H38: 1 | I38: 1 | J38: 1 | K38: 1 | L38: 1 | M38: 1 | N38: 1 | O38: 1
B39: WASH: Agua corriente o entubada | C39: 1 | D39: 1 | E39: 1 | F39: 1 | G39: 1 | H39: 1 | I39: 1 | J39: 1 | K39: 1 | L39: 1 | M39: 1 | N39: 1 | O39: 1

Sheet Opciones de la curva de costos
A1: Lineal (costo marginal constante) [por defecto]
A2: Curva con costo marginal creciente
A3: Curva con costo marginal decreciente
A4: En forma de S (costo marginal decreciente y luego creciente)

Sheet Prog. de planificación familiar
A1: Método | B1: Efectividad | C1: Distribución | D1: Costo | E1: Costo proporcional
A2: Preservativo/condón | B2: 0.9 | C2: 0.09 | D2: 0.8 | E2: =C2*D2 -> 0.072
A3: Esterilización masculina | B3: 1 | C3: 0.02 | D3: 1.9 | E3: =C3*D3 -> 0.038
A4: Esterilización femenina | B4: 1 | C4: 0.08 | D4: 2 | E4: =C4*D4 -> 0.16
A5: Inyectable | B5: 1 | C5: 0.18 | D5: 0.7 | E5: =C5*D5 -> 0.126
A6: Implante | B6: 1 | C6: 0.02 | D6: 0.7 | E6: =C6*D6 -> 0.014
A7: Cápsula/píldora | B7: 0.93 | C7: 0.45 | D7: 0.9 | E7: =C7*D7 -> 0.405
A8: Retiro | B8: 0.5 | C8: 0.03 | D8: 0 | E8: =C8*D8 -> 0
A9: Planificación Familiar Natural | B9: 0.5 | C9: 0.11 | D9: 0 | E9: =C9*D9 -> 0
A10: Dispositivo Intrauterino (DIU) | B10: 0.98 | C10: 0.01 | D10: 0.6 | E10: =C10*D10 -> 0.006

Sheet Programas población afectada
A1: Amplio grupo de población | B1: Programa | C1: <1 mes | D1: 1-5 meses | E1: 6-11 meses | F1: 12-23 meses | G1: 24-59 meses | H1: PW: 15-19 años | I1: PW: 20-29 años | J1: PW: 30-39 años | K1: PW: 40-49 años | L1: WRA: 15-19 años (mujeres en edad reproductiva) | M1: WRA: 20-29 años (mujeres en edad reproductiva) | N1: WRA: 30-39 años (mujeres en edad reproductiva) | O1: WRA: 40-49 años (mujeres en edad reproductiva)
A2: Niños | B2: Transferencias de efectivo | C2: 0 | D2: 0 | E2: 1 | F2: 1 | G2: 0 | H2: 0 | I2: 0 | J2: 0 | K2: 0 | L2: 0 | M2: 0 | N2: 0 | O2: 0
B3: Retraso en el pinzamiento del cordón umbilical | C3: 1 | D3: 1 | E3: 0 | F3: 0 | G3: 0 | H3: 0 | I3: 0 | J3: 0 | K3: 0 | L3: 0 | M3: 0 | N3: 0 | O3: 0
B4: IYCF 1-alimentación del lactante y del niño pequeño | C4: 1 | D4: 1 | E4: 1 | F4: 1 | G4: 1 | H4: 0 | I4: 0 | J4: 0 | K4: 0 | L4: 0 | M4: 0 | N4: 0 | O4: 0
B5: IYCF 2-alimentación del lactante y del niño pequeño | C5: 1 | D5: 1 | E5: 1 | F5: 1 | G5: 1 | H5: 0 | I5: 0 | J5: 0 | K5: 0 | L5: 0 | M5: 0 | N5: 0 | O5: 0
B6: IYCF 3-alimentación del lactante y del niño pequeño | C6: 1 | D6: 1 | E6: 1 | F6: 1 | G6: 1 | H6: 0 | I6: 0 | J6: 0 | K6: 0 | L6: 0 | M6: 0 | N6: 0 | O6: 0
B7: Método de la madre canguro | C7: 1 | D7: 1 | E7: 0 | F7: 0 | G7: 0 | H7: 0 | I7: 0 | J7: 0 | K7: 0 | L7: 0 | M7: 0 | N7: 0 | O7: 0
B8: Suplementos nutricionales a base de lípidos | C8: 0 | D8: 0 | E8: 1 | F8: 1 | G8: 0 | H8: 0 | I8: 0 | J8: 0 | K8: 0 | L8: 0 | M8: 0 | N8: 0 | O8: 0
B9: Micronutrientes en polvo | C9: 0 | D9: 0 | E9: 1 | F9: 1 | G9: 1 | H9: 0 | I9: 0 | J9: 0 | K9: 0 | L9: 0 | M9: 0 | N9: 0 | O9: 0
B10: Sales de rehidratación oral | C10: 1 | D10: 1 | E10: 1 | F10: 1 | G10: 1 | H10: 0 | I10: 0 | J10: 0 | K10: 0 | L10: 0 | M10: 0 | N10: 0 | O10: 0
B11: Suministro público de alimentos complementarios | C11: 0 | D11: 0 | E11: 1 | F11: 1 | G11: 0 | H11: 0 | I11: 0 | J11: 0 | K11: 0 | L11: 0 | M11: 0 | N11: 0 | O11: 0
B12: Suplementos nutricionales a base de lípidos en pequeñas cantidades | C12: 0 | D12: 0 | E12: 1 | F12: 1 | G12: 0 | H12: 0 | I12: 0 | J12: 0 | K12: 0 | L12: 0 | M12: 0 | N12: 0 | O12: 0
B13: Tratamiento de la MAS | C13: 0 | D13: 1 | E13: 1 | F13: 1 | G13: 1 | H13: 0 | I13: 0 | J13: 0 | K13: 0 | L13: 0 | M13: 0 | N13: 0 | O13: 0
B14: Suplementación con vitamina A | C14: 0 | D14: 0 | E14: 1 | F14: 1 | G14: 1 | H14: 0 | I14: 0 | J14: 0 | K14: 0 | L14: 0 | M14: 0 | N14: 0 | O14: 0
... B16: Suplementación con zinc | C16: 0 | D16: 0 | E16: 1 | F16: 1 | G16: 1 | H16: 0 | I16: 0 | J16: 0 | K16: 0 | L16: 0 | M16: 0 | N16: 0 | O16: 0
A18: Mujeres embarazadas | B18: Suplemento energético-proteico equilibrado | C18: 0 | D18: 0 | E18: 0 | F18: 0 | G18: 0 | H18: 1 | I18: 1 | J18: 1 | K18: 1 | L18: 0 | M18: 0 | N18: 0 | O18: 0
B19: Suplemento con calcio | C19: 0 | D19: 0 | E19: 0 | F19: 0 | G19: 0 | H19: 1 | I19: 1 | J19: 1 | K19: 1 | L19: 0 | M19: 0 | N19: 0 | O19: 0
B20: Suplementación con hierro y ácido fólico para mujeres embarazadas (comunidad) | C20: 0 | D20: 0 | E20: 0 | F20: 0 | G20: 0 | H20: 1 | I20: 1 | J20: 1 | K20: 1 | L20: 0 | M20: 0 | N20: 0 | O20: 0
B21: Suplementación con hierro y ácido fólico para mujeres embarazadas (centro de salud) | C21: 0 | D21: 0 | E21: 0 | F21: 0 | G21: 0 | H21: 1 | I21: 1 | J21: 1 | K21: 1 | L21: 0 | M21: 0 | N21: 0 | O21: 0
B22: IPTp-Tratamiento preventivo intermitente de la malaria en el embarazo | C22: 0 | D22: 0 | E22: 0 | F22: 0 | G22: 0 | H22: 1 | I22: 1 | J22: 1 | K22: 1 | L22: 0 | M22: 0 | N22: 0 | O22: 0
B23: Magnesio para la eclampsia | C23: 0 | D23: 0 | E23: 0 | F23: 0 | G23: 0 | H23: 1 | I23: 1 | J23: 1 | K23: 1 | L23: 0 | M23: 0 | N23: 0 | O23: 0
B24: Magnesio para la preeclampsia | C24: 0 | D24: 0 | E24: 0 | F24: 0 | G24: 0 | H24: 1 | I24: 1 | J24: 1 | K24: 1 | L24: 0 | M24: 0 | N24: 0 | O24: 0
B25: Suplementación con micronutrientes múltiples | C25: 0 | D25: 0 | E25: 0 | F25: 0 | G25: 0 | H25: 1 | I25: 1 | J25: 1 | K25: 1 | L25: 0 | M25: 0 | N25: 0 | O25: 0
A27: Mujeres en edad reproductiva no embarazadas | B27: Planificación familiar | C27: 0 | D27: 0 | E27: 0 | F27: 0 | G27: 0 | H27: 0 | I27: 0 | J27: 0 | K27: 0 | L27: 1 | M27: 0 | N27: 0 | O27: 0
B28: Suplementación con hierro y ácido fólico (comunidad) | C28: 0 | D28: 0 | E28: 0 | F28: 0 | G28: 0 | H28: 0 | I28: 0 | J28: 0 | K28: 0 | L28: 1 | M28: 1 | N28: 1 | O28: 1
B29: Suplementación con hierro y ácido fólico (centro de salud) | C29: 0 | D29: 0 | E29: 0 | F29: 0 | G29: 0 | H29: 0 | I29: 0 | J29: 0 | K29: 0 | L29: 1 | M29: 1 | N29: 1 | O29: 1
B30: Suplementación con hierro y ácido fólico (minorista) | C30: 0 | D30: 0 | E30: 0 | F30: 0 | G30: 0 | H30: 0 | I30: 0 | J30: 0 | K30: 0 | L30: 1 | M30: 1 | N30: 1 | O30: 1
B31: Suplementación con hierro y ácido fólico (escuela) | C31: 0 | D31: 0 | E31: 0 | F31: 0 | G31: 0 | H31: 0 | I31: 0 | J31: 0 | K31: 0 | L31: 1 | M31: 0 | N31: 0 | O31: 0
A33: Población general | B33: Enriquecimiento del maíz con hierro y ácido fólico | C33: 1 | D33: 0 | E33: 1 | F33: 1 | G33: 1 | H33: 1 | I33: 1 | J33: 1 | K33: 1 | L33: 1 | M33: 1 | N33: 1 | O33: 1
B34: Enriquecimiento del arroz con hierro y ácido fólico | C34: 1 | D34: 0 | E34: 1 | F34: 1 | G34: 1 | H34: 1 | I34: 1 | J34: 1 | K34: 1 | L34: 1 | M34: 1 | N34: 1 | O34: 1
B35: Enriquecimiento de la harina de trigo con hierro y ácido fólico | C35: 1 | D35: 0 | E35: 1 | F35: 1 | G35: 1 | H35: 1 | I35: 1 | J35: 1 | K35: 1 | L35: 1 | M35: 1 | N35: 1 | O35: 1
B36: Fortificación de la sal con hierro y yodo | C36: 1 | D36: 0 | E36: 1 | F36: 1 | G36: 1 | H36: 1 | I36: 1 | J36: 1 | K36: 1 | L36: 1 | M36: 1 | N36: 1 | O36: 1
B37: Mosquiteros tratados con insecticida de larga duración | C37: 1 | D37: 1 | E37: 1 | F37: 1 | G37: 1 | H37: 1 | I37: 1 | J37: 1 | K37: 1 | L37: 1 | M37: 1 | N37: 1 | O37: 1
B38: WASH: Lavado de manos | C38: 1 | D38: 1 | E38: 1 | F38: 1 | G38: 1 | H38: 1 | I38: 1 | J38: 1 | K38: 1 | L38: 1 | M38: 1 | N38: 1 | O38: 1
B39: WASH: Eliminación higiénica de residuos | C39: 1 | D39: 1 | E39: 1 | F39: 1 | G39: 1 | H39: 1 | I39: 1 | J39: 1 | K39: 1 | L39: 1 | M39: 1 | N39: 1 | O39: 1
B40: WASH: Mejora del saneamiento | C40: 1 | D40: 1 | E40: 1 | F40: 1 | G40: 1 | H40: 1 | I40: 1 | J40: 1 | K40: 1 | L40: 1 | M40: 1 | N40: 1 | O40: 1
B41: WASH: Mejora de la fuente de agua | C41: 1 | D41: 1 | E41: 1 | F41: 1 | G41: 1 | H41: 1 | I41: 1 | J41: 1 | K41: 1 | L41: 1 | M41: 1 | N41: 1 | O41: 1
B42: WASH: Agua corriente o entubada | C42: 1 | D42: 1 | E42: 1 | F42: 1 | G42: 1 | H42: 1 | I42: 1 | J42: 1 | K42: 1 | L42: 1 | M42: 1 | N42: 1 | O42: 1

Sheet Riesgos que impacta programa
A1: Programa | B1: Baja talla o retraso en el crecimiento | C1: Anemia | D1: Prevención de la emaciación | E1: Tratamiento de la emaciación | F1: Lactancia materna | G1: Diarrea | H1: Mortalidad | I1: Desenlaces del nacimiento | J1: Espaciamiento entre los nacimientos | K1: Número de nacimiento | L1: Mortinatos
A2: Suplemento energético-proteico equilibrado | I2: x
A3: Suplemento con calcio | H3: x | I3: x
A4: Transferencias de efectivo | B4: x | D4: x
A5: Retraso en el pinzamiento del cordón umbilical | C5: x
A6: Planificación familiar | J6: x | K6: x
A7: Enriquecimiento del maíz con hierro y ácido fólico | C7: x | H7: x
A8: Enriquecimiento del arroz con hierro y ácido fólico | C8: x | H8: x
A9: Enriquecimiento de la harina de trigo con hierro y ácido fólico | C9: x | H9: x
A10: Suplementación con hierro y ácido fólico (comunidad) | C10: x
A11: Suplementación con hierro y ácido fólico (centro de salud) | C11: x
A12: Suplementación con hierro y ácido fólico (minorista) | C12: x
A13: Suplementación con hierro y ácido fólico (escuela) | C13: x
A14: Suplementación con hierro y ácido fólico para mujeres embarazadas (comunidad) | C14: x | I14: x
A15: Suplementación con hierro y ácido fólico para mujeres embarazadas (centro de salud) | C15: x | I15: x
A16: IPTp-Tratamiento preventivo intermitente de la malaria en el embarazo | C16: x | H16: x | I16: x
A17: Fortificación de la sal con hierro y yodo | C17: x
A18: IYCF 1-alimentación del lactante y del niño pequeño | B18: x | F18: x
A19: IYCF 2-alimentación del lactante y del niño pequeño | B19: x | F19: x
A20: IYCF 3-alimentación del lactante y del niño pequeño | B20: x | F20: x
A21: Método de la madre canguro | H21: x | I21: x
A22: Suplementos nutricionales a base de lípidos | B22: x | C22: x | D22: x
A23: Mosquiteros tratados con insecticida de larga duración | C23: x | I23: x
A24: Magnesio para la eclampsia | H24: x
A25: Magnesio para la preeclampsia | H25: x
A26: Micronutrientes en polvo | C26: x
A27: Suplementación con micronutrientes múltiples | C27: x | I27: x | L27: x
A28: Sales de rehidratación oral | H28: x
A29: Suministro público de alimentos complementarios | B29: x | D29: x
A30: Suplementos nutricionales a base de lípidos en pequeñas cantidades | B30: x | C30: x | D30: x
A31: Tratamiento de la MAS | E31: x
A32: Suplementación con vitamina A | G32: x | H32: x
A33: WASH: Lavado de manos | G33: x | H33: x
A34: WASH: Eliminación higiénica de residuos | G34: x | H34: x
A35: WASH: Mejora del saneamiento | G35: x | H35: x
A36: WASH: Mejora de la fuente de agua | G36: x | H36: x
A37: WASH: Agua corriente o entubada | G37: x | H37: x
A38: Zinc para el tratamiento + SRO | H38: x
A39: Suplementación con zinc | B39: x | G39: x | H39: x

Sheet Riegos para la población
A1: Rango de edades | B1: Baja talla o retraso en el crecimiento | C1: Anemia | D1: Prevención de la emaciación | E1: Tratamiento de la emaciación | F1: Lactancia materna | G1: Diarrea | H1: Mortalidad | I1: Desenlaces del nacimiento | J1: Espaciamiento entre los nacimientos | K1: Número de nacimiento | L1: Mortinatos
A2: <1 mes | B2: x | C2: x | D2: x | E2: x | F2: x | G2: x | H2: x
A3: 1-5 meses | B3: x | C3: x | D3: x | E3: x | F3: x | G3: x | H3: x
A4: 6-11 meses | B4: x | C4: x | D4: x | E4: x | F4: x | G4: x | H4: x
A5: 12-23 meses | B5: x | C5: x | D5: x | E5: x | F5: x | G5: x | H5: x
A6: 24-59 meses | B6: x | C6: x | D6: x | E6: x | F6: x | G6: x | H6: x
A7: PW: 15-19 años | C7: x | H7: x | I7: x | L7: x
A8: PW: 20-29 años | C8: x | H8: x | I8: x | L8: x
A9: PW: 30-39 años | C9: x | H9: x | I9: x | L9: x
A10: PW: 40-49 años | C10: x | H10: x | I10: x | L10: x
A11: WRA: 15-19 años (mujeres en edad reproductiva) | C11: x | J11: x | K11: x
A12: WRA: 20-29 años (mujeres en edad reproductiva) | C12: x | K12: x
A13: WRA: 30-39 años (mujeres en edad reproductiva) | C13: x | K13: x
A14: WRA: 40-49 años (mujeres en edad reproductiva) | C14: x | K14: x

Sheet Razón de momios IYCF
A1: Comportamiento | B1: Población objetivo | C1: Método de entrega | D1: <1 mes | E1: 1-5 meses | F1: 6-11 meses | G1: 12-23 meses | H1: 24-59 meses
A2: Razón de momios para lactancia materna adecuada | B2: Mujeres embarazadas | C2: Centro de salud | D2: 1 | E2: 1 | F2: 1 | G2: 1 | H2: 1
C3: Comunidad | D3: 1 | E3: 1 | F3: 1 | G3: 1 | H3: 1
C4: Medios de comunicación masivos | D4: 1 | E4: 1 | F4: 1 | G4: 1 | H4: 1
B5: <1 mes | C5: Centro de salud | D5: 2.17 | E5: 1 | F5: 1 | G5: 1 | H5: 1
C6: Comunidad | D6: 2.17 | E6: 1 | F6: 1 | G6: 1 | H6: 1
C7: Medios de comunicación masivos | D7: 1 | E7: 1 | F7: 1 | G7: 1 | H7: 1
B8: 1-5 meses | C8: Centro de salud | D8: 1 | E8: 2.48 | F8: 1 | G8: 1 | H8: 1
C9: Comunidad | D9: 1 | E9: 2.48 | F9: 1 | G9: 1 | H9: 1
C10: Medios de comunicación masivos | D10: 1 | E10: 1 | F10: 1 | G10: 1 | H10: 1
B11: 6-11 meses | C11: Centro de salud | D11: 1 | E11: 1 | F11: 1.82 | G11: 1 | H11: 1
C12: Comunidad | D12: 1 | E12: 1 | F12: 1.82 | G12: 1 | H12: 1
C13: Medios de comunicación masivos | D13: 1 | E13: 1 | F13: 1 | G13: 1 | H13: 1
B14: 12-23 meses | C14: Centro de salud | D14: 1 | E14: 1 | F14: 1 | G14: 1.82 | H14: 1
C15: Comunidad | D15: 1 | E15: 1 | F15: 1 | G15: 1.82 | H15: 1
C16: Medios de comunicación masivos | D16: 1 | E16: 1 | F16: 1 | G16: 1 | H16: 1
B17: Todo | C17: Medios de comunicación masivos | D17: 1.05 | E17: 1.05 | F17: 1.05 | G17: 1.05 | H17: 1
A19: Razón de momios para baja talla o retraso en el crecimiento | B19: Mujeres embarazadas | C19: Centro de salud | D19: 1 | E19: 1 | F19: 1 | G19: 1 | H19: 1
C20: Comunidad | D20: 1 | E20: 1 | F20: 1 | G20: 1 | H20: 1
C21: Medios de comunicación masivos | D21: 1 | E21: 1 | F21: 1 | G21: 1 | H21: 1
B22: <1 mes | C22: Centro de salud | D22: 1 | E22: 1 | F22: 1 | G22: 1 | H22: 1
C23: Comunidad | D23: 1 | E23: 1 | F23: 1 | G23: 1 | H23: 1
C24: Medios de comunicación masivos | D24: 1 | E24: 1 | F24: 1 | G24: 1 | H24: 1
B25: 1-5 meses | C25: Centro de salud | D25: 1 | E25: 1 | F25: 1 | G25: 1 | H25: 1
C26: Comunidad | D26: 1 | E26: 1 | F26: 1 | G26: 1 | H26: 1
C27: Medios de comunicación masivos | D27: 1 | E27: 1 | F27: 1 | G27: 1 | H27: 1
B28: 6-11 meses | C28: Centro de salud | D28: 1 | E28: 1 | F28: 1 | G28: 1 | H28: 1
C29: Comunidad | D29: 1 | E29: 1 | F29: 1 | G29: 1 | H29: 1
C30: Medios de comunicación masivos | D30: 1 | E30: 1 | F30: 1 | G30: 1 | H30: 1
B31: 12-23 meses | C31: Centro de salud | D31: 1 | E31: 1 | F31: 1 | G31: 1 | H31: 1
C32: Comunidad | D32: 1 | E32: 1 | F32: 1 | G32: 1 | H32: 1
C33: Medios de comunicación masivos | D33: 1 | E33: 1 | F33: 1 | G33: 1 | H33: 1
B34: Todo | C34: Medios de comunicación masivos | D34: 1 | E34: 1 | F34: 1 | G34: 1 | H34: 1
A36: Razón de momios para alimentación complementaria correcta | B36: Mujeres embarazadas | C36: Centro de salud | D36: 1 | E36: 1 | F36: 1 | G36: 1 | H36: 1
C37: Comunidad | D37: 1 | E37: 1 | F37: 1 | G37: 1 | H37: 1
C38: Medios de comunicación masivos | D38: 1 | E38: 1 | F38: 1 | G38: 1 | H38: 1
B39: <1 mes | C39: Centro de salud | D39: 1 | E39: 1 | F39: 1 | G39: 1 | H39: 1
C40: Comunidad | D40: 1 | E40: 1 | F40: 1 | G40: 1 | H40: 1
C41: Medios de comunicación masivos | D41: 1 | E41: 1 | F41: 1 | G41: 1 | H41: 1
B42: 1-5 meses | C42: Centro de salud | D42: 1 | E42: 1 | F42: 1 | G42: 1 | H42: 1
C43: Comunidad | D43: 1 | E43: 1 | F43: 1 | G43: 1 | H43: 1
C44: Medios de comunicación masivos | D44: 1 | E44: 1 | F44: 1 | G44: 1 | H44: 1
B45: 6-11 meses | C45: Centro de salud | D45: 1 | E45: 1 | F45: 1 | G45: 1 | H45: 1
C46: Comunidad | D46: 1 | E46: 1 | F46: 1 | G46: 1 | H46: 1
C47: Medios de comunicación masivos | D47: 1 | E47: 1 | F47: 1 | G47: 1 | H47: 1
B48: 12-23 meses | C48: Centro de salud | D48: 1 | E48: 1 | F48: 1 | G48: 1 | H48: 1
C49: Comunidad | D49: 1 | E49: 1 | F49: 1 | G49: 1 | H49: 1
C50: Medios de comunicación masivos | D50: 1 | E50: 1 | F50: 1 | G50: 1 | H50: 1
B51: Todo | C51: Medios de comunicación masivos | D51: 1 | E51: 1 | F51: 1 | G51: 1 | H51: 1
A53: Límites inferiores
A54: Comportamiento | B54: Población objetivo | C54: Método de entrega | D54: <1 mes | E54: 1-5 meses | F54: 6-11 meses | G54: 12-23 meses | H54: 24-59 meses
A55: Razón de momios para lactancia materna adecuada- inferior | B55: Mujeres embarazadas | C55: Centro de salud | D55: =IF(D2=1,1,D2*0.9) -> 1 | E55: =IF(E2=1,1,E2*0.9) -> 1 | F55: =IF(F2=1,1,F2*0.9) -> 1 | G55: =IF(G2=1,1,G2*0.9) -> 1 | H55: =IF(H2=1,1,H2*0.9) -> 1
C56: Comunidad | D56: =IF(D3=1,1,D3*0.9) -> 1 | E56: =IF(E3=1,1,E3*0.9) -> 1 | F56: =IF(F3=1,1,F3*0.9) -> 1 | G56: =IF(G3=1,1,G3*0.9) -> 1 | H56: =IF(H3=1,1,H3*0.9) -> 1
C57: Medios de comunicación masivos | D57: =IF(D4=1,1,D4*0.9) -> 1 | E57: =IF(E4=1,1,E4*0.9) -> 1 | F57: =IF(F4=1,1,F4*0.9) -> 1 | G57: =IF(G4=1,1,G4*0.9) -> 1 | H57: =IF(H4=1,1,H4*0.9) -> 1
B58: <1 mes | C58: Centro de salud | D58: 1.84 | E58: =IF(E5=1,1,E5*0.9) -> 1 | F58: =IF(F5=1,1,F5*0.9) -> 1 | G58: =IF(G5=1,1,G5*0.9) -> 1 | H58: =IF(H5=1,1,H5*0.9) -> 1
C59: Comunidad | D59: 1.84 | E59: =IF(E6=1,1,E6*0.9) -> 1 | F59: =IF(F6=1,1,F6*0.9) -> 1 | G59: =IF(G6=1,1,G6*0.9) -> 1 | H59: =IF(H6=1,1,H6*0.9) -> 1
C60: Medios de comunicación masivos | D60: =IF(D7=1,1,D7*0.9) -> 1 | E60: =IF(E7=1,1,E7*0.9) -> 1 | F60: =IF(F7=1,1,F7*0.9) -> 1 | G60: =IF(G7=1,1,G7*0.9) -> 1 | H60: =IF(H7=1,1,H7*0.9) -> 1
B61: 1-5 meses | C61: Centro de salud | D61: =IF(D8=1,1,D8*0.9) -> 1 | E61: 1.99 | F61: =IF(F8=1,1,F8*0.9) -> 1 | G61: =IF(G8=1,1,G8*0.9) -> 1 | H61: =IF(H8=1,1,H8*0.9) -> 1
C62: Comunidad | D62: =IF(D9=1,1,D9*0.9) -> 1 | E62: 1.99 | F62: =IF(F9=1,1,F9*0.9) -> 1 | G62: =IF(G9=1,1,G9*0.9) -> 1 | H62: =IF(H9=1,1,H9*0.9) -> 1
C63: Medios de comunicación masivos | D63: =IF(D10=1,1,D10*0.9) -> 1 | E63: =IF(E10=1,1,E10*0.9) -> 1 | F63: =IF(F10=1,1,F10*0.9) -> 1 | G63: =IF(G10=1,1,G10*0.9) -> 1 | H63: =IF(H10=1,1,H10*0.9) -> 1
B64: 6-11 meses | C64: Centro de salud | D64: =IF(D11=1,1,D11*0.9) -> 1 | E64: =IF(E11=1,1,E11*0.9) -> 1 | F64: 1.36 | G64: =IF(G11=1,1,G11*0.9) -> 1 | H64: =IF(H11=1,1,H11*0.9) -> 1
C65: Comunidad | D65: =IF(D12=1,1,D12*0.9) -> 1 | E65: =IF(E12=1,1,E12*0.9) -> 1 | F65: 1.36 | G65: =IF(G12=1,1,G12*0.9) -> 1 | H65: =IF(H12=1,1,H12*0.9) -> 1
C66: Medios de comunicación masivos | D66: =IF(D13=1,1,D13*0.9) -> 1 | E66: =IF(E13=1,1,E13*0.9) -> 1 | F66: =IF(F13=1,1,F13*0.9) -> 1 | G66: =IF(G13=1,1,G13*0.9) -> 1 | H66: =IF(H13=1,1,H13*0.9) -> 1
B67: 12-23 meses | C67: Centro de salud | D67: =IF(D14=1,1,D14*0.9) -> 1 | E67: =IF(E14=1,1,E14*0.9) -> 1 | F67: =IF(F14=1,1,F14*0.9) -> 1 | G67: 1.36 | H67: =IF(H14=1,1,H14*0.9) -> 1
C68: Comunidad | D68: =IF(D15=1,1,D15*0.9) -> 1 | E68: =IF(E15=1,1,E15*0.9) -> 1 | F68: =IF(F15=1,1,F15*0.9) -> 1 | G68: 1.36 | H68: =IF(H15=1,1,H15*0.9) -> 1
C69: Medios de comunicación masivos | D69: =IF(D16=1,1,D16*0.9) -> 1 | E69: =IF(E16=1,1,E16*0.9) -> 1 | F69: =IF(F16=1,1,F16*0.9) -> 1 | G69: =IF(G16=1,1,G16*0.9) -> 1 | H69: =IF(H16=1,1,H16*0.9) -> 1
B70: Todo | C70: Medios de comunicación masivos | D70: =IF(D17=1,1,D17*0.9) -> 0.945 | E70: =IF(E17=1,1,E17*0.9) -> 0.945 | F70: =IF(F17=1,1,F17*0.9) -> 0.945 | G70: =IF(G17=1,1,G17*0.9) -> 0.945 | H70: =IF(H17=1,1,H17*0.9) -> 1
A72: Razón de momios para baja talla - inferior | B72: Mujeres embarazadas | C72: Centro de salud | D72: =IF(D19=1,1,D19*0.9) -> 1 | E72: =IF(E19=1,1,E19*0.9) -> 1 | F72: =IF(F19=1,1,F19*0.9) -> 1 | G72: =IF(G19=1,1,G19*0.9) -> 1 | H72: =IF(H19=1,1,H19*0.9) -> 1
C73: Comunidad | D73: =IF(D20=1,1,D20*0.9) -> 1 | E73: =IF(E20=1,1,E20*0.9) -> 1 | F73: =IF(F20=1,1,F20*0.9) -> 1 | G73: =IF(G20=1,1,G20*0.9) -> 1 | H73: =IF(H20=1,1,H20*0.9) -> 1
C74: Medios de comunicación masivos | D74: =IF(D21=1,1,D21*0.9) -> 1 | E74: =IF(E21=1,1,E21*0.9) -> 1 | F74: =IF(F21=1,1,F21*0.9) -> 1 | G74: =IF(G21=1,1,G21*0.9) -> 1 | H74: =IF(H21=1,1,H21*0.9) -> 1
B75: <1 mes | C75: Centro de salud | D75: =IF(D22=1,1,D22*0.9) -> 1 | E75: =IF(E22=1,1,E22*0.9) -> 1 | F75: =IF(F22=1,1,F22*0.9) -> 1 | G75: =IF(G22=1,1,G22*0.9) -> 1 | H75: =IF(H22=1,1,H22*0.9) -> 1
C76: Comunidad | D76: =IF(D23=1,1,D23*0.9) -> 1 | E76: =IF(E23=1,1,E23*0.9) -> 1 | F76: =IF(F23=1,1,F23*0.9) -> 1 | G76: =IF(G23=1,1,G23*0.9) -> 1 | H76: =IF(H23=1,1,H23*0.9) -> 1
C77: Medios de comunicación masivos | D77: =IF(D24=1,1,D24*0.9) -> 1 | E77: =IF(E24=1,1,E24*0.9) -> 1 | F77: =IF(F24=1,1,F24*0.9) -> 1 | G77: =IF(G24=1,1,G24*0.9) -> 1 | H77: =IF(H24=1,1,H24*0.9) -> 1
B78: 1-5 meses | C78: Centro de salud | D78: =IF(D25=1,1,D25*0.9) -> 1 | E78: =IF(E25=1,1,E25*0.9) -> 1 | F78: =IF(F25=1,1,F25*0.9) -> 1 | G78: =IF(G25=1,1,G25*0.9) -> 1 | H78: =IF(H25=1,1,H25*0.9) -> 1
C79: Comunidad | D79: =IF(D26=1,1,D26*0.9) -> 1 | E79: =IF(E26=1,1,E26*0.9) -> 1 | F79: =IF(F26=1,1,F26*0.9) -> 1 | G79: =IF(G26=1,1,G26*0.9) -> 1 | H79: =IF(H26=1,1,H26*0.9) -> 1
C80: Medios de comunicación masivos | D80: =IF(D27=1,1,D27*0.9) -> 1 | E80: =IF(E27=1,1,E27*0.9) -> 1 | F80: =IF(F27=1,1,F27*0.9) -> 1 | G80: =IF(G27=1,1,G27*0.9) -> 1 | H80: =IF(H27=1,1,H27*0.9) -> 1
B81: 6-11 meses | C81: Centro de salud | D81: =IF(D28=1,1,D28*0.9) -> 1 | E81: =IF(E28=1,1,E28*0.9) -> 1 | F81: =IF(F28=1,1,F28*0.9) -> 1 | G81: =IF(G28=1,1,G28*0.9) -> 1 | H81: =IF(H28=1,1,H28*0.9) -> 1
C82: Comunidad | D82: =IF(D29=1,1,D29*0.9) -> 1 | E82: =IF(E29=1,1,E29*0.9) -> 1 | F82: =IF(F29=1,1,F29*0.9) -> 1 | G82: =IF(G29=1,1,G29*0.9) -> 1 | H82: =IF(H29=1,1,H29*0.9) -> 1
C83: Medios de comunicación masivos | D83: =IF(D30=1,1,D30*0.9) -> 1 | E83: =IF(E30=1,1,E30*0.9) -> 1 | F83: =IF(F30=1,1,F30*0.9) -> 1 | G83: =IF(G30=1,1,G30*0.9) -> 1 | H83: =IF(H30=1,1,H30*0.9) -> 1
B84: 12-23 meses | C84: Centro de salud | D84: =IF(D31=1,1,D31*0.9) -> 1 | E84: =IF(E31=1,1,E31*0.9) -> 1 | F84: =IF(F31=1,1,F31*0.9) -> 1 | G84: =IF(G31=1,1,G31*0.9) -> 1 | H84: =IF(H31=1,1,H31*0.9) -> 1
C85: Comunidad | D85: =IF(D32=1,1,D32*0.9) -> 1 | E85: =IF(E32=1,1,E32*0.9) -> 1 | F85: =IF(F32=1,1,F32*0.9) -> 1 | G85: =IF(G32=1,1,G32*0.9) -> 1 | H85: =IF(H32=1,1,H32*0.9) -> 1
C86: Medios de comunicación masivos | D86: =IF(D33=1,1,D33*0.9) -> 1 | E86: =IF(E33=1,1,E33*0.9) -> 1 | F86: =IF(F33=1,1,F33*0.9) -> 1 | G86: =IF(G33=1,1,G33*0.9) -> 1 | H86: =IF(H33=1,1,H33*0.9) -> 1
B87: Todo | C87: Medios de comunicación masivos | D87: =IF(D34=1,1,D34*0.9) -> 1 | E87: =IF(E34=1,1,E34*0.9) -> 1 | F87: =IF(F34=1,1,F34*0.9) -> 1 | G87: =IF(G34=1,1,G34*0.9) -> 1 | H87: =IF(H34=1,1,H34*0.9) -> 1
A89: Razón de momios para alimentación complementaria correcta - inferior | B89: Mujeres embarazadas | C89: Centro de salud | D89: =IF(D36=1,1,D36*0.9) -> 1 | E89: =IF(E36=1,1,E36*0.9) -> 1 | F89: =IF(F36=1,1,F36*0.9) -> 1 | G89: =IF(G36=1,1,G36*0.9) -> 1 | H89: =IF(H36=1,1,H36*0.9) -> 1
C90: Comunidad | D90: =IF(D37=1,1,D37*0.9) -> 1 | E90: =IF(E37=1,1,E37*0.9) -> 1 | F90: =IF(F37=1,1,F37*0.9) -> 1 | G90: =IF(G37=1,1,G37*0.9) -> 1 | H90: =IF(H37=1,1,H37*0.9) -> 1
C91: Medios de comunicación masivos | D91: =IF(D38=1,1,D38*0.9) -> 1 | E91: =IF(E38=1,1,E38*0.9) -> 1 | F91: =IF(F38=1,1,F38*0.9) -> 1 | G91: =IF(G38=1,1,G38*0.9) -> 1 | H91: =IF(H38=1,1,H38*0.9) -> 1
B92: <1 mes | C92: Centro de salud | D92: =IF(D39=1,1,D39*0.9) -> 1 | E92: =IF(E39=1,1,E39*0.9) -> 1 | F92: =IF(F39=1,1,F39*0.9) -> 1 | G92: =IF(G39=1,1,G39*0.9) -> 1 | H92: =IF(H39=1,1,H39*0.9) -> 1
C93: Comunidad | D93: =IF(D40=1,1,D40*0.9) -> 1 | E93: =IF(E40=1,1,E40*0.9) -> 1 | F93: =IF(F40=1,1,F40*0.9) -> 1 | G93: =IF(G40=1,1,G40*0.9) -> 1 | H93: =IF(H40=1,1,H40*0.9) -> 1
C94: Medios de comunicación masivos | D94: =IF(D41=1,1,D41*0.9) -> 1 | E94: =IF(E41=1,1,E41*0.9) -> 1 | F94: =IF(F41=1,1,F41*0.9) -> 1 | G94: =IF(G41=1,1,G41*0.9) -> 1 | H94: =IF(H41=1,1,H41*0.9) -> 1
B95: 1-5 meses | C95: Centro de salud | D95: =IF(D42=1,1,D42*0.9) -> 1 | E95: =IF(E42=1,1,E42*0.9) -> 1 | F95: =IF(F42=1,1,F42*0.9) -> 1 | G95: =IF(G42=1,1,G42*0.9) -> 1 | H95: =IF(H42=1,1,H42*0.9) -> 1
C96: Comunidad | D96: =IF(D43=1,1,D43*0.9) -> 1 | E96: =IF(E43=1,1,E43*0.9) -> 1 | F96: =IF(F43=1,1,F43*0.9) -> 1 | G96: =IF(G43=1,1,G43*0.9) -> 1 | H96: =IF(H43=1,1,H43*0.9) -> 1
C97: Medios de comunicación masivos | D97: =IF(D44=1,1,D44*0.9) -> 1 | E97: =IF(E44=1,1,E44*0.9) -> 1 | F97: =IF(F44=1,1,F44*0.9) -> 1 | G97: =IF(G44=1,1,G44*0.9) -> 1 | H97: =IF(H44=1,1,H44*0.9) -> 1
B98: 6-11 meses | C98: Centro de salud | D98: =IF(D45=1,1,D45*0.9) -> 1 | E98: =IF(E45=1,1,E45*0.9) -> 1 | F98: =IF(F45=1,1,F45*0.9) -> 1 | G98: =IF(G45=1,1,G45*0.9) -> 1 | H98: =IF(H45=1,1,H45*0.9) -> 1
C99: Comunidad | D99: =IF(D46=1,1,D46*0.9) -> 1 | E99: =IF(E46=1,1,E46*0.9) -> 1 | F99: =IF(F46=1,1,F46*0.9) -> 1 | G99: =IF(G46=1,1,G46*0.9) -> 1 | H99: =IF(H46=1,1,H46*0.9) -> 1
C100: Medios de comunicación masivos | D100: =IF(D47=1,1,D47*0.9) -> 1 | E100: =IF(E47=1,1,E47*0.9) -> 1 | F100: =IF(F47=1,1,F47*0.9) -> 1 | G100: =IF(G47=1,1,G47*0.9) -> 1 | H100: =IF(H47=1,1,H47*0.9) -> 1
B101: 12-23 meses | C101: Centro de salud | D101: =IF(D48=1,1,D48*0.9) -> 1 | E101: =IF(E48=1,1,E48*0.9) -> 1 | F101: =IF(F48=1,1,F48*0.9) -> 1 | G101: =IF(G48=1,1,G48*0.9) -> 1 | H101: =IF(H48=1,1,H48*0.9) -> 1
C102: Comunidad | D102: =IF(D49=1,1,D49*0.9) -> 1 | E102: =IF(E49=1,1,E49*0.9) -> 1 | F102: =IF(F49=1,1,F49*0.9) -> 1 | G102: =IF(G49=1,1,G49*0.9) -> 1 | H102: =IF(H49=1,1,H49*0.9) -> 1
C103: Medios de comunicación masivos | D103: =IF(D50=1,1,D50*0.9) -> 1 | E103: =IF(E50=1,1,E50*0.9) -> 1 | F103: =IF(F50=1,1,F50*0.9) -> 1 | G103: =IF(G50=1,1,G50*0.9) -> 1 | H103: =IF(H50=1,1,H50*0.9) -> 1
B104: Todo | C104: Medios de comunicación masivos | D104: =IF(D51=1,1,D51*0.9) -> 1 | E104: =IF(E51=1,1,E51*0.9) -> 1 | F104: =IF(F51=1,1,F51*0.9) -> 1 | G104: =IF(G51=1,1,G51*0.9) -> 1 | H104: =IF(H51=1,1,H51*0.9) -> 1
A106: Límites superiores
...

Sheet Razón de momios
A1: Razón de momios de baja talla o retraso en el crecimiento
A2: Condición | C2: <1 mes | D2: 1-5 meses | E2: 6-11 meses | F2: 12-23 meses | G2: 24-59 meses
B3: Dada la baja talla previa (HAZ < -2 en la banda de edad anterior) | C3: N/A | D3: 45 | E3: 361.6 | F3: 174.7 | G3: 174.7
B4: Diarrea (por episodio adicional) | C4: 1.025 | D4: 1.025 | E4: 1.025 | F4: 1.025 | G4: 1.025
A5: Por programa
B6: Suministro público de alimentos complementarios | C6: 1 | D6: 1 | E6: 0.89 | F6: 0.89 | G6: 1
B7: Suplementos nutricionales a base de lípidos | C7: 1 | D7: 1 | E7: 0.88 | F7: 0.88 | G7: 1
B8: Transferencias de efectivo | C8: 1 | D8: 1 | E8: 1 | F8: 0.808 | G8: 0.808
B9: Suplementos nutricionales a base de lípidos en pequeñas cantidades | C9: 1 | D9: 1 | E9: 0.88 | F9: 0.88 | G9: 1
B10: Suplementación con zinc | C10: 1 | D10: 1 | E10: 1 | F10: 1 | G10: 1
A12: Razón de momios de lactancia materna adecuada por programa
B13: Método de la madre canguro | C13: 1 | D13: 1.39 | E13: 1 | F13: 1 | G13: 1
A15: Otras razones de momios
A16: Emaciación | B16: Para MAS por episodio adicional de diarrea | C16: 1.024 | D16: 1.024 | E16: 1.024 | F16: 1.024 | G16: 1.024
B17: Para MAM por episodio adicional de diarrea | C17: 1.024 | D17: 1.024 | E17: 1.024 | F17: 1.024 | G17: 1.024
A18: Anemia | B18: Para anemia por episodio adicional de diarrea grave | C18: 1 | D18: 1 | E18: 1 | F18: 1 | G18: 1
A20: Razón de momios para el espaciamiento óptimo de los nacimientos por programa
C21: WRA: 15-19 años (mujeres en edad reproductiva) | D21: WRA: 20-29 años (mujeres en edad reproductiva) | E21: WRA: 30-39 años (mujeres en edad reproductiva) | F21: WRA: 40-49 años (mujeres en edad reproductiva)
B22: Planificación familiar | C22: 1.52 | D22: 1 | E22: 1 | F22: 1
A24: Límites inferiores
A25: Razón de momios de baja talla o retraso en el crecimiento
A26: Condición | C26: <1 mes | D26: 1-5 meses | E26: 6-11 meses | F26: 12-23 meses | G26: 24-59 meses
B27: Dada a baja talla previa (HAZ < -2 en la banda de edad anterior) - inferior | C27: N/A | D27: =D3*0.9 -> 40.5 | E27: =E3*0.9 -> 325.44 | F27: =F3*0.9 -> 157.23 | G27: =G3*0.9 -> 157.23
B28: Diarrea (por episodio adicional) - inferior | C28: 1.014 | D28: 1.014 | E28: 1.014 | F28: 1.014 | G28: 1.014
A29: Por programa - inferior
B30: Suministro público de alimentos complementarios - inferior | C30: =IF(C6=1,1,C6*0.9) -> 1 | D30: =IF(D6=1,1,D6*0.9) -> 1 | E30: =E6*0.9 -> 0.801 | F30: =F6*0.9 -> 0.801 | G30: =IF(G6=1,1,G6*0.9) -> 1
B31: Suplementos nutricionales a base de lípidos: más bajos | C31: =IF(C7=1,1,C7*0.9) -> 1 | D31: =IF(D7=1,1,D7*0.9) -> 1 | E31: 0.85 | F31: 0.85 | G31: =IF(G7=1,1,G7*0.9) -> 1
B32: Cash transfers - lower | C32: =IF(C8=1,1,C8*0.9) -> 1 | D32: =IF(D8=1,1,D8*0.9) -> 1 | E32: 1 | F32: 0.395 | G32: 0.395
B33: Suplementos nutricionales a base de lípidos en pequeñas cantidades: lower | C33: =IF(C9=1,1,C9*0.9) -> 1 | D33: =IF(D9=1,1,D9*0.9) -> 1 | E33: 0.85 | F33: 0.85 | G33: =IF(G9=1,1,G9*0.9) -> 1
B34: Suplementación con zinc - inferior | C34: =IF(C10=1,1,C10*0.9) -> 1 | D34: =IF(D10=1,1,D10*0.9) -> 1 | E34: =IF(E10=1,1,E10*0.9) -> 1 | F34: =IF(F10=1,1,F10*0.9) -> 1 | G34: =IF(G10=1,1,G10*0.9) -> 1
A36: Razón de momios de lactancia materna adecuada por programa - inferior
B37: Método madre canguro - inferior | C37: 1 | D37: 1.11 | E37: 1 | F37: 1 | G37: 1
A39: Otras razones de momios
A40: Emaciación | B40: Para MAS por episodio adicional de diarrea - inferior | C40: 1.016 | D40: 1.016 | E40: 1.016 | F40: 1.016 | G40: 1.016
B41: Para MAM por episodio adicional de diarrea - inferior | C41: 1.016 | D41: 1.016 | E41: 1.016 | F41: 1.016 | G41: 1.016
A42: Anemia | B42: Para anemia por episodio adicional de diarrea grave - inferior | C42: =IF(C18=1,1,C18*0.9) -> 1 | D42: =IF(D18=1,1,D18*0.9) -> 1 | E42: =IF(E18=1,1,E18*0.9) -> 1 | F42: =IF(F18=1,1,F18*0.9) -> 1 | G42: =IF(G18=1,1,G18*0.9) -> 1
A44: Razón de momios para el espaciamiento óptimo de los nacimientos por programa - inferior
C45: WRA: 15-19 años (mujeres en edad reproductiva) | D45: WRA: 20-29 años (mujeres en edad reproductiva) | E45: WRA: 30-39 años (mujeres en edad reproductiva) | F45: WRA: 40-49 años (mujeres en edad reproductiva)
B46: Planificación familiar - más baja | C46: =C22*0.9 -> 1.368 | D46: 1 | E46: 1 | F46: 1
A48: Límites superiores
A49: Razón de momios de baja talla o retraso en el crecimiento
A50: Condición | C50: <1 mes | D50: 1-5 meses | E50: 6-11 meses | F50: 12-23 meses | G50: 24-59 meses
B51: Dada la baja talla previa (HAZ < -2 en la banda de edad anterior) - superior | C51: N/A | D51: =D3*1.05 -> 47.25 | E51: =E3*1.05 -> 379.68 | F51: =F3*1.05 -> 183.435 | G51: =G3*1.05 -> 183.435
B52: Diarrea (por episodio adicional) - superior | C52: 1.035 | D52: 1.035 | E52: 1.035 | F52: 1.035 | G52: 1.035
A53: Por programa - superior
B54: Suministro público de alimentos complementarios - superior | C54: =IF(C6=1,1,C6*1.1) -> 1 | D54: =IF(D6=1,1,D6*1.1) -> 1 | E54: =E6*1.05 -> 0.9345 | F54: =F6*1.05 -> 0.9345 | G54: =IF(G6=1,1,G6*1.1) -> 1
B55: Suplementos nutricionales a base de lípidos - superior | C55: =IF(C7=1,1,C7*1.1) -> 1 | D55: =IF(D7=1,1,D7*1.1) -> 1 | E55: 0.91 | F55: 0.91 | G55: =IF(G7=1,1,G7*1.1) -> 1
B56: Cash transfers - upper | C56: =IF(C8=1,1,C8*1.1) -> 1 | D56: =IF(D8=1,1,D8*1.1) -> 1 | E56: 1 | F56: 0.956 | G56: 0.956
B57: Suplementos nutricionales a base de lípidos en pequeñas cantidades - superior | C57: =IF(C9=1,1,C9*1.1) -> 1 | D57: =IF(D9=1,1,D9*1.1) -> 1 | E57: 0.91 | F57: 0.91 | G57: =IF(G9=1,1,G9*1.1) -> 1
B58: Suplementación con zinc- superior | C58: =IF(C10=1,1,C10*1.1) -> 1 | D58: =IF(D10=1,1,D10*1.1) -> 1 | E58: =IF(E10=1,1,E10*1.1) -> 1 | F58: =IF(F10=1,1,F10*1.1) -> 1 | G58: =IF(G10=1,1,G10*1.1) -> 1
A60: Razón de momios de lactancia materna adecuada por programa - superior
B61: Método madre canguro - superior | C61: 1 | D61: 1.74 | E61: 1 | F61: 1 | G61: 1
A63: Otras razones de momios
A64: Emaciación | B64: Para MAS por episodio adicional de diarrea - superior | C64: 1.031 | D64: 1.031 | E64: 1.031 | F64: 1.031 | G64: 1.031
B65: Para MAM por episodio adicional de diarrea - superior | C65: 1.031 | D65: 1.031 | E65: 1.031 | F65: 1.031 | G65: 1.031
A66: Anemia | B66: Para anemia por episodio adicional de diarrea grave - superior | C66: =IF(C18=1,1,C18*1.1) -> 1 | D66: =IF(D18=1,1,D18*1.1) -> 1 | E66: =IF(E18=1,1,E18*1.1) -> 1 | F66: =IF(F18=1,1,F18*1.1) -> 1 | G66: =IF(G18=1,1,G18*1.1) -> 1
A68: Razón de momios para el espaciamiento óptimo de los nacimientos por programa - superior
C69: WRA: 15-19 años (mujeres en edad reproductiva) | D69: WRA: 20-29 años (mujeres en edad reproductiva) | E69: WRA: 30-39 años (mujeres en edad reproductiva) | F69: WRA: 40-49 años (mujeres en edad reproductiva)
B70: Planificación familiar - superior | C70: =C22*1.1 -> 1.672 | D70: 1 | E70: 1 | F70: 1

Sheet Resultados de nacimiento- prog
A1: Programa | C1: Prematuro PEG (pequeño para la edad gestacional) | D1: Nacido a término PEG (pequeño para la edad gestacional) | E1: Prematuro AEG (adecuado para edad gestacional) | F1: Nacido a término AEG (Adecuado para la edad gestacional)
A2: Suplemento energético-proteico equilibrado | B2: efectividad | C2: 0.29 | D2: 0.29 | E2: 0 | F2: 0
B3: fracción afectada | C3: 1 | D3: 1 | E3: 1 | F3: 1
A4: Suplemento con calcio | B4: efectividad | C4: =1-0.76 -> 0.24 | D4: 0 | E4: =1-0.76 -> 0.24 | F4: 0
B5: fracción afectada | C5: 1 | D5: 1 | E5: 1 | F5: 1
A6: Suplementación con hierro y ácido fólico para mujeres embarazadas (comunidad) | B6: efectividad | C6: 0.61 | D6: 0.61 | E6: 0 | F6: 0
B7: fracción afectada | C7: 1 | D7: 1 | E7: 1 | F7: 1
A8: Suplementación con hierro y ácido fólico para mujeres embarazadas (centro de salud) | B8: efectividad | C8: 0.61 | D8: 0.61 | E8: 0 | F8: 0
B9: fracción afectada | C9: 1 | D9: 1 | E9: 1 | F9: 1
A10: IPTp-Tratamiento preventivo intermitente de la malaria en el embarazo | B10: efectividad | C10: 0.35 | D10: 0.35 | E10: 0 | F10: 0
B11: fracción afectada | C11: 1 | D11: 1 | E11: 0 | F11: 0
A12: Mosquiteros tratados con insecticida de larga duración | B12: efectividad | C12: 0.35 | D12: 0.35 | E12: 0 | F12: 0
B13: fracción afectada | C13: 1 | D13: 1 | E13: 0 | F13: 0
A14: Suplementación con micronutrientes múltiples | B14: efectividad | C14: =1-0.9*0.39 -> 0.649 | D14: =1-0.9*0.39 -> 0.649 | E14: 0 | F14: 0
B15: fracción afectada | C15: 1 | D15: 1 | E15: 1 | F15: 1
A17: Límites inferiores
A18: Programa | C18: Prematuro PEG (pequeño para la edad gestacional) | D18: Nacido a término PEG (pequeño para la edad gestacional) | E18: Prematuro AEG (adecuado para edad gestacional) | F18: Nacido a término AEG (Adecuado para la edad gestacional)
A19: Suplemento energético-proteico equilibrado | B19: efectividad | C19: =1-0.94 -> 0.06 | D19: =1-0.94 -> 0.06 | E19: =E2*0.9 -> 0 | F19: =F2*0.9 -> 0
B20: fracción afectada | C20: 1 | D20: 1 | E20: 1 | F20: 1
A21: Suplemento con calcio | B21: efectividad | C21: =1-0.97 -> 0.03 | D21: 0 | E21: =1-0.97 -> 0.03 | F21: 0
B22: fracción afectada | C22: 1 | D22: 1 | E22: 1 | F22: 1
A23: Suplementación con hierro y ácido fólico para mujeres embarazadas (comunidad) | B23: efectividad | C23: =1-0.86 -> 0.14 | D23: =1-0.86 -> 0.14 | E23: =E6*0.9 -> 0 | F23: =F6*0.9 -> 0
B24: fracción afectada | C24: 1 | D24: 1 | E24: 1 | F24: 1
A25: Suplementación con hierro y ácido fólico para mujeres embarazadas (centro de salud) | B25: efectividad | C25: =1-0.86 -> 0.14 | D25: =1-0.86 -> 0.14 | E25: =E8*0.9 -> 0 | F25: =F8*0.9 -> 0
B26: fracción afectada | C26: 1 | D26: 1 | E26: 1 | F26: 1
A27: IPTp-Tratamiento preventivo intermitente de la malaria en el embarazo | B27: efectividad | C27: =1-0.77 -> 0.23 | D27: =1-0.77 -> 0.23 | E27: =E12*0.9 -> 0 | F27: =F12*0.9 -> 0
B28: fracción afectada | C28: 1 | D28: 1 | E28: 1 | F28: 1
A29: Mosquiteros tratados con insecticida de larga duración | B29: efectividad | C29: =1-0.77 -> 0.23 | D29: =1-0.77 -> 0.23 | E29: =E12*0.9 -> 0 | F29: =F12*0.9 -> 0
B30: fracción afectada | C30: 1 | D30: 1 | E30: 1 | F30: 1
A31: Suplementación con micronutrientes múltiples | B31: efectividad | C31: =1-0.96*0.86 -> 0.1744 | D31: =1-0.96*0.86 -> 0.1744 | E31: =E14*0.9 -> 0 | F31: =F14*0.9 -> 0
B32: fracción afectada | C32: 1 | D32: 1 | E32: 1 | F32: 1
A34: Límites superiores
A35: Programa | C35: Prematuro PEG (pequeño para la edad gestacional) | D35: Nacido a término PEG (pequeño para la edad gestacional) | E35: Prematuro AEG (adecuado para edad gestacional) | F35: Nacido a término AEG (Adecuado para la edad gestacional)
A36: Suplemento energético-proteico equilibrado | B36: efectividad | C36: =1-0.54 -> 0.46 | D36: =1-0.54 -> 0.46 | E36: =E2*1.1 -> 0 | F36: =F2*1.1 -> 0
B37: fracción afectada | C37: 1 | D37: 1 | E37: 1 | F37: 1
A38: Suplemento con calcio | B38: efectividad | C38: =1-0.6 -> 0.4 | D38: 0 | E38: =1-0.6 -> 0.4 | F38: 0
B39: fracción afectada | C39: 1 | D39: 1 | E39: 1 | F39: 1
A40: Suplementación con hierro y ácido fólico para mujeres embarazadas (comunidad) | B40: efectividad | C40: =1-0.17 -> 0.83 | D40: =1-0.17 -> 0.83 | E40: =E6*1.1 -> 0 | F40: =F6*1.1 -> 0
B41: fracción afectada | C41: 1 | D41: 1 | E41: 1 | F41: 1
A42: Suplementación con hierro y ácido fólico para mujeres embarazadas (centro de salud) | B42: efectividad | C42: =1-0.17 -> 0.83 | D42: =1-0.17 -> 0.83 | E42: =E8*1.1 -> 0 | F42: =F8*1.1 -> 0
B43: fracción afectada | C43: 1 | D43: 1 | E43: 1 | F43: 1
A44: IPTp-Tratamiento preventivo intermitente de la malaria en el embarazo | B44: efectividad | C44: =1-0.55 -> 0.45 | D44: =1-0.55 -> 0.45 | E44: =E10*1.1 -> 0 | F44: =F10*1.1 -> 0
B45: fracción afectada | C45: 1 | D45: 1 | E45: 1 | F45: 1
A46: Mosquiteros tratados con insecticida de larga duración | B46: efectividad | C46: =1-0.55 -> 0.45 | D46: =1-0.55 -> 0.45 | E46: =E12*1.1 -> 0 | F46: =F12*1.1 -> 0
B47: fracción afectada | C47: 1 | D47: 1 | E47: 1 | F47: 1
A48: Suplementación con micronutrientes múltiples | B48: efectividad | C48: =1-0.84*0.17 -> 0.8572 | D48: =1-0.84*0.17 -> 0.8572 | E48: =E14*1.1 -> 0 | F48: =F14*1.1 -> 0
B49: fracción afectada | C49: 1 | D49: 1 | E49: 1 | F49: 1

Sheet Riesgos desenlace de nacimiento
A1: Factores de riesgo materno que conducen a los resultados del nacimiento
C2: Nacido a término AEG (Adecuado para la edad gestacional) | D2: Nacido a término PEG (pequeño para la edad gestacional) | E2: Prematuro AEG (adecuado para edad gestacional) | F2: Prematuro PEG (pequeño para la edad gestacional)
A3: Riesgo relativo según el espaciamiento de los nacimientos
B4: El primer nacimiento | C4: 1 | D4: 1 | E4: 1 | F4: 1
B5: menos de 18 meses | C5: 1 | D5: 1.41 | E5: 1.49 | F5: 3.03
B6: 18-23 meses | C6: 1 | D6: 1.18 | E6: 1.1 | F6: 1.77
B7: 24 meses o más | C7: 1 | D7: 1 | E7: 1 | F7: 1
A9: Razón de momios para mujeres con anemia materna | C9: 1 | D9: 1.53 | E9: 1.32 | F9: 1.53
A11: Riesgos para los niños que experimentan desenlaces al nacimiento
A12: Razón de momios para las condiciones
B13: Retraso en el crecimiento (score HAZ < -2) | C13: 1 | D13: 5 | E13: 6.4 | F13: 46.5
B14: MAM (puntuación WHZ entre -3 y -2) | C14: 1 | D14: 2.52 | E14: 1.96 | F14: 4.19
B15: MAS (score WHZ < -3) | C15: 1 | D15: 2.52 | E15: 1.96 | F15: 4.19
A17: Riesgos relativos de las causas de muerte neonatal
B18: Diarrea neonatal | C18: 1 | D18: 1 | E18: 1 | F18: 1
B19: Sepsis neonatal | C19: 1 | D19: 2.07 | E19: 3.39 | F19: 11.89
B20: Neumonía neonatal | C20: 1 | D20: 2.07 | E20: 3.39 | F20: 11.89
B21: Asfixia neonatal | C21: 1 | D21: 2.07 | E21: 3.39 | F21: 11.89
B22: Prematuridad neonatal | C22: 1 | D22: 1 | E22: 999.99 | F22: 999.99
B23: Tétanos neonatal | C23: 1 | D23: 1 | E23: 1 | F23: 1
B24: Anomalías congénitas neonatales | C24: 1 | D24: 1 | E24: 1 | F24: 1
B25: Neonatal otros | C25: 1 | D25: 1 | E25: 1 | F25: 1
A27: Límites inferiores
A28: Factores de riesgo materno que conducen a los resultados del nacimiento
C29: Nacido a término AEG (Adecuado para la edad gestacional) | D29: Nacido a término PEG (pequeño para la edad gestacional) | E29: Prematuro AEG (adecuado para edad gestacional) | F29: Prematuro PEG (pequeño para la edad gestacional)
A30: Riesgo relativo según el espaciamiento de los nacimientos-inferior
B31: El primer nacimiento | C31: =IF(C4=1,1,C4*0.9) -> 1 | D31: =IF(D4=1,1,D4*0.9) -> 1 | E31: =IF(E4=1,1,E4*0.9) -> 1 | F31: =IF(F4=1,1,F4*0.9) -> 1
B32: menos de 18 meses | C32: =IF(C5=1,1,C5*0.9) -> 1 | D32: =IF(D5=1,1,D5*0.9) -> 1.269 | E32: =IF(E5=1,1,E5*0.9) -> 1.341 | F32: =IF(F5=1,1,F5*0.9) -> 2.727
B33: 18-23 meses | C33: =IF(C6=1,1,C6*0.9) -> 1 | D33: =IF(D6=1,1,D6*0.9) -> 1.062 | E33: =IF(E6=1,1,E6*0.9) -> 0.99 | F33: =IF(F6=1,1,F6*0.9) -> 1.593
B34: 24 meses o más | C34: =IF(C7=1,1,C7*0.9) -> 1 | D34: =IF(D7=1,1,D7*0.9) -> 1 | E34: =IF(E7=1,1,E7*0.9) -> 1 | F34: =IF(F7=1,1,F7*0.9) -> 1
A36: Razón de momios para mujeres con anemia materna-inferior | C36: =IF(C9=1,1,C9*0.9) -> 1 | D36: =IF(D9=1,1,D9*0.9) -> 1.377 | E36: =IF(E9=1,1,E9*0.9) -> 1.188 | F36: =IF(F9=1,1,F9*0.9) -> 1.377
A38: Riesgos para los niños que experimentan desenlaces al nacimiento
A39: Razón de momios para las condiciones - inferior
B40: Retraso en el crecimiento (score HAZ < -2)-Inferior | C40: =IF(C13=1,1,C13*0.9) -> 1 | D40: =IF(D13=1,1,D13*0.9) -> 4.5 | E40: =IF(E13=1,1,E13*0.9) -> 5.76 | F40: =IF(F13=1,1,F13*0.9) -> 41.85
B41: MAM (puntuación WHZ entre -3 y -2)-inferior | C41: =IF(C14=1,1,C14*0.9) -> 1 | D41: =IF(D14=1,1,D14*0.9) -> 2.268 | E41: =IF(E14=1,1,E14*0.9) -> 1.764 | F41: =IF(F14=1,1,F14*0.9) -> 3.771
B42: MAS (score WHZ < -3)-Inferior | C42: =IF(C15=1,1,C15*0.9) -> 1 | D42: =IF(D15=1,1,D15*0.9) -> 2.268 | E42: =IF(E15=1,1,E15*0.9) -> 1.764 | F42: =IF(F15=1,1,F15*0.9) -> 3.771
A44: Riesgos relativos de las causas de muerte neonatal - inferior
B45: Diarrea neonatal | C45: =IF(C18=1,1,C18*0.9) -> 1 | D45: =IF(D18=1,1,D18*0.9) -> 1 | E45: =IF(E18=1,1,E18*0.9) -> 1 | F45: =IF(F18=1,1,F18*0.9) -> 1
B46: Sepsis neonatal | C46: =IF(C19=1,1,C19*0.9) -> 1 | D46: =IF(D19=1,1,D19*0.9) -> 1.863 | E46: =IF(E19=1,1,E19*0.9) -> 3.051 | F46: =IF(F19=1,1,F19*0.9) -> 10.701
B47: Neumonía neonatal | C47: =IF(C20=1,1,C20*0.9) -> 1 | D47: =IF(D20=1,1,D20*0.9) -> 1.863 | E47: =IF(E20=1,1,E20*0.9) -> 3.051 | F47: =IF(F20=1,1,F20*0.9) -> 10.701
B48: Asfixia neonatal | C48: =IF(C21=1,1,C21*0.9) -> 1 | D48: =IF(D21=1,1,D21*0.9) -> 1.863 | E48: =IF(E21=1,1,E21*0.9) -> 3.051 | F48: =IF(F21=1,1,F21*0.9) -> 10.701
B49: Prematuridad neonatal | C49: =IF(C22=1,1,C22*0.9) -> 1 | D49: =IF(D22=1,1,D22*0.9) -> 1 | E49: =IF(E22=1,1,E22*0.9) -> 899.991 | F49: =IF(F22=1,1,F22*0.9) -> 899.991
B50: Tétanos neonatal | C50: =IF(C23=1,1,C23*0.9) -> 1 | D50: =IF(D23=1,1,D23*0.9) -> 1 | E50: =IF(E23=1,1,E23*0.9) -> 1 | F50: =IF(F23=1,1,F23*0.9) -> 1
B51: Anomalías congénitas neonatales | C51: =IF(C24=1,1,C24*0.9) -> 1 | D51: =IF(D24=1,1,D24*0.9) -> 1 | E51: =IF(E24=1,1,E24*0.9) -> 1 | F51: =IF(F24=1,1,F24*0.9) -> 1
B52: Neonatal otros | C52: =IF(C25=1,1,C25*0.9) -> 1 | D52: =IF(D25=1,1,D25*0.9) -> 1 | E52: =IF(E25=1,1,E25*0.9) -> 1 | F52: =IF(F25=1,1,F25*0.9) -> 1
A54: Límites superiores
A55: Factores de riesgo materno que conducen a los resultados del nacimiento
C56: Nacido a término AEG (Adecuado para la edad gestacional) | D56: Nacido a término PEG (pequeño para la edad gestacional) | E56: Prematuro AEG (adecuado para edad gestacional) | F56: Prematuro PEG (pequeño para la edad gestacional)
A57: Riesgo relativo según el espaciamiento de los nacimientos - superior
B58: El primer nacimiento | C58: =IF(C4=1,1,C4*1.1) -> 1 | D58: =IF(D4=1,1,D4*1.1) -> 1 | E58: =IF(E4=1,1,E4*1.1) -> 1 | F58: =IF(F4=1,1,F4*1.1) -> 1
B59: menos de 18 meses | C59: =IF(C5=1,1,C5*1.1) -> 1 | D59: =IF(D5=1,1,D5*1.1) -> 1.551 | E59: =IF(E5=1,1,E5*1.1) -> 1.639 | F59: =IF(F5=1,1,F5*1.1) -> 3.333
B60: 18-23 meses | C60: =IF(C6=1,1,C6*1.1) -> 1 | D60: =IF(D6=1,1,D6*1.1) -> 1.298 | E60: =IF(E6=1,1,E6*1.1) -> 1.21 | F60: =IF(F6=1,1,F6*1.1) -> 1.947
B61: 24 meses o más | C61: =IF(C7=1,1,C7*1.1) -> 1 | D61: =IF(D7=1,1,D7*1.1) -> 1 | E61: =IF(E7=1,1,E7*1.1) -> 1 | F61: =IF(F7=1,1,F7*1.1) -> 1
A63: Razón de momios para mujeres con anemia materna-superior | C63: =IF(C9=1,1,C9*1.1) -> 1 | D63: =IF(D9=1,1,D9*1.1) -> 1.683 | E63: =IF(E9=1,1,E9*1.1) -> 1.452 | F63: =IF(F9=1,1,F9*1.1) -> 1.683
A65: Riesgos para los niños que experimentan desenlaces al nacimiento
A66: Razón de momios para las condiciones - superior
B67: Retraso en el crecimiento (score HAZ < -2)-superior | C67: =IF(C13=1,1,C13*1.1) -> 1 | D67: =IF(D13=1,1,D13*1.1) -> 5.5 | E67: =IF(E13=1,1,E13*1.1) -> 7.04 | F67: =IF(F13=1,1,F13*1.1) -> 51.15
B68: MAM (puntuación WHZ entre -3 y -2)-superior | C68: =IF(C14=1,1,C14*1.1) -> 1 | D68: =IF(D14=1,1,D14*1.1) -> 2.772 | E68: =IF(E14=1,1,E14*1.1) -> 2.156 | F68: =IF(F14=1,1,F14*1.1) -> 4.609
B69: MAS (score WHZ < -3)-superior | C69: =IF(C15=1,1,C15*1.1) -> 1 | D69: =IF(D15=1,1,D15*1.1) -> 2.772 | E69: =IF(E15=1,1,E15*1.1) -> 2.156 | F69: =IF(F15=1,1,F15*1.1) -> 4.609
A71: Riesgos relativos de las causas de muerte neonatal - superior
B72: Diarrea neonatal | C72: =IF(C18=1,1,C18*1.1) -> 1 | D72: =IF(D18=1,1,D18*1.1) -> 1 | E72: =IF(E18=1,1,E18*1.1) -> 1 | F72: =IF(F18=1,1,F18*1.1) -> 1
B73: Sepsis neonatal | C73: =IF(C19=1,1,C19*1.1) -> 1 | D73: =IF(D19=1,1,D19*1.1) -> 2.277 | E73: =IF(E19=1,1,E19*1.1) -> 3.729 | F73: =IF(F19=1,1,F19*1.1) -> 13.079
B74: Neumonía neonatal | C74: =IF(C20=1,1,C20*1.1) -> 1 | D74: =IF(D20=1,1,D20*1.1) -> 2.277 | E74: =IF(E20=1,1,E20*1.1) -> 3.729 | F74: =IF(F20=1,1,F20*1.1) -> 13.079
B75: Asfixia neonatal | C75: =IF(C21=1,1,C21*1.1) -> 1 | D75: =IF(D21=1,1,D21*1.1) -> 2.277 | E75: =IF(E21=1,1,E21*1.1) -> 3.729 | F75: =IF(F21=1,1,F21*1.1) -> 13.079
B76: Prematuridad neonatal | C76: =IF(C22=1,1,C22*1.1) -> 1 | D76: =IF(D22=1,1,D22*1.1) -> 1 | E76: =IF(E22=1,1,E22*1.1) -> 1099.989 | F76: =IF(F22=1,1,F22*1.1) -> 1099.989
B77: Tétanos neonatal | C77: =IF(C23=1,1,C23*1.1) -> 1 | D77: =IF(D23=1,1,D23*1.1) -> 1 | E77: =IF(E23=1,1,E23*1.1) -> 1 | F77: =IF(F23=1,1,F23*1.1) -> 1
B78: Anomalías congénitas neonatales | C78: =IF(C24=1,1,C24*1.1) -> 1 | D78: =IF(D24=1,1,D24*1.1) -> 1 | E78: =IF(E24=1,1,E24*1.1) -> 1 | F78: =IF(F24=1,1,F24*1.1) -> 1
B79: Neonatal otros | C79: =IF(C25=1,1,C25*1.1) -> 1 | D79: =IF(D25=1,1,D25*1.1) -> 1 | E79: =IF(E25=1,1,E25*1.1) -> 1 | F79: =IF(F25=1,1,F25*1.1) -> 1

Sheet Riesgos relativos
A1: Riesgo relativo de las causas de muerte según la distribución de talla para la edad (retraso en el crecimiento)
A2: Baja talla o retraso en el crecimiento | B2: Causa de muerte | C2: Estado de HAZ (baja talla) | D2: <1 mes | E2: 1-5 meses | F2: 6-11 meses | G2: 12-23 meses | H2: 24-59 meses
B3: Diarrea | C3: Normal | D3: 1 | E3: 1 | F3: 1 | G3: 1 | H3: 1
C4: Leve | D4: 1 | E4: 1.67 | F4: 1.67 | G4: 1.67 | H4: 1.67
C5: Moderado | D5: 1 | E5: 2.38 | F5: 2.38 | G5: 2.38 | H5: 2.38
C6: Alto | D6: 1 | E6: 6.33 | F6: 6.33 | G6: 6.33 | H6: 6.33
B7: Neumonía | C7: Normal | D7: 1 | E7: 1 | F7: 1 | G7: 1 | H7: 1
C8: Leve | D8: 1 | E8: 1.55 | F8: 1.55 | G8: 1.55 | H8: 1.55
C9: Moderado | D9: 1 | E9: 2.18 | F9: 2.18 | G9: 2.18 | H9: 2.18
C10: Alto | D10: 1 | E10: 6.39 | F10: 6.39 | G10: 6.39 | H10: 6.39
B11: Sarampión | C11: Normal | D11: 1 | E11: 1 | F11: 1 | G11: 1 | H11: 1
C12: Leve | D12: 1 | E12: 1 | F12: 1 | G12: 1 | H12: 1
C13: Moderado | D13: 1 | E13: 2.79 | F13: 2.79 | G13: 2.79 | H13: 2.79
C14: Alto | D14: 1 | E14: 6.01 | F14: 6.01 | G14: 6.01 | H14: 6.01
B15: Malaria | C15: Normal | D15: 1 | E15: 1 | F15: 1 | G15: 1 | H15: 1
C16: Leve | D16: 1 | E16: 1 | F16: 1 | G16: 1 | H16: 1
C17: Moderado | D17: 1 | E17: 1 | F17: 1 | G17: 1 | H17: 1
C18: Alto | D18: 1 | E18: 1 | F18: 1 | G18: 1 | H18: 1
B19: Meningitis | C19: Normal | D19: 1 | E19: 1 | F19: 1 | G19: 1 | H19: 1
C20: Leve | D20: 1 | E20: 1 | F20: 1 | G20: 1 | H20: 1
C21: Moderado | D21: 1 | E21: 1.86 | F21: 1.86 | G21: 1.86 | H21: 1.86
C22: Alto | D22: 1 | E22: 3.01 | F22: 3.01 | G22: 3.01 | H22: 3.01
B23: Otro | C23: Normal | D23: 1 | E23: 1 | F23: 1 | G23: 1 | H23: 1
C24: Leve | D24: 1 | E24: 1 | F24: 1 | G24: 1 | H24: 1
C25: Moderado | D25: 1 | E25: 1.86 | F25: 1.86 | G25: 1.86 | H25: 1.86
C26: Alto | D26: 1 | E26: 3.01 | F26: 3.01 | G26: 3.01 | H26: 3.01
A28: Riesgo relativo de las causas de muerte según la distribución del peso para la talla (emaciación)
A29: Emaciación | B29: Causa de muerte | C29: Estado de la peso para la talla (WHZ) | D29: <1 mes | E29: 1-5 meses | F29: 6-11 meses | G29: 12-23 meses | H29: 24-59 meses
B30: Diarrea | C30: Normal | D30: 1 | E30: 1 | F30: 1 | G30: 1 | H30: 1
C31: Leve | D31: 1 | E31: 1.6 | F31: 1.6 | G31: 1.6 | H31: 1.6
C32: MAM | D32: 1 | E32: 3.41 | F32: 3.41 | G32: 3.41 | H32: 3.41
C33: MAS | D33: 1 | E33: 12.33 | F33: 12.33 | G33: 12.33 | H33: 12.33
B34: Neumonía | C34: Normal | D34: 1 | E34: 1 | F34: 1 | G34: 1 | H34: 1
C35: Leve | D35: 1 | E35: 1.92 | F35: 1.92 | G35: 1.92 | H35: 1.92
C36: MAM | D36: 1 | E36: 4.66 | F36: 4.66 | G36: 4.66 | H36: 4.66
C37: MAS | D37: 1 | E37: 9.68 | F37: 9.68 | G37: 9.68 | H37: 9.68
B38: Sarampión | C38: Normal | D38: 1 | E38: 1 | F38: 1 | G38: 1 | H38: 1
C39: Leve | D39: 1 | E39: 1 | F39: 1 | G39: 1 | H39: 1
C40: MAM | D40: 1 | E40: 2.58 | F40: 2.58 | G40: 2.58 | H40: 2.58
C41: MAS | D41: 1 | E41: 9.63 | F41: 9.63 | G41: 9.63 | H41: 9.63
B42: Malaria | C42: Normal | D42: 1 | E42: 1 | F42: 1 | G42: 1 | H42: 1
C43: Leve | D43: 1 | E43: 1 | F43: 1 | G43: 1 | H43: 1
C44: MAM | D44: 1 | E44: 1 | F44: 1 | G44: 1 | H44: 1
C45: MAS | D45: 1 | E45: 1 | F45: 1 | G45: 1 | H45: 1
B46: Meningitis | C46: Normal | D46: 1 | E46: 1 | F46: 1 | G46: 1 | H46: 1
C47: Leve | D47: 1 | E47: 1.65 | F47: 1.65 | G47: 1.65 | H47: 1.65
C48: MAM | D48: 1 | E48: 2.73 | F48: 2.73 | G48: 2.73 | H48: 2.73
C49: MAS | D49: 1 | E49: 11.21 | F49: 11.21 | G49: 11.21 | H49: 11.21
B50: Otro | C50: Normal | D50: 1 | E50: 1 | F50: 1 | G50: 1 | H50: 1
C51: Leve | D51: 1 | E51: 1.65 | F51: 1.65 | G51: 1.65 | H51: 1.65
C52: MAM | D52: 1 | E52: 2.73 | F52: 2.73 | G52: 2.73 | H52: 2.73
C53: MAS | D53: 1 | E53: 11.21 | F53: 11.21 | G53: 11.21 | H53: 11.21
A55: Riesgo relativo de las causas de muerte según el estado de la anemia
A56: Anemia | B56: Causa de muerte | C56: Estado de anemia | D56: PW: 15-19 años | E56: PW: 20-29 años | F56: PW: 30-39 años | G56: PW: 40-49 años
B57: Hemorragia pre-parto | C57: No anémico | D57: 1 | E57: 1 | F57: 1 | G57: 1
C58: Anémico | D58: 10.675 | E58: 10.675 | F58: 10.675 | G58: 10.675
B59: Hemorragia intraparto | C59: No anémico | D59: 1 | E59: 1 | F59: 1 | G59: 1
C60: Anémico | D60: 10.675 | E60: 10.675 | F60: 10.675 | G60: 10.675
B61: Hemorragia posparto | C61: No anémico | D61: 1 | E61: 1 | F61: 1 | G61: 1
C62: Anémico | D62: 10.675 | E62: 10.675 | F62: 10.675 | G62: 10.675
A64: Riesgo relativo de las causas de muerte según el estado de la lactancia materna
A65: Lactancia materna | B65: Causa de muerte | C65: Situación de lactancia materna | D65: <1 mes | E65: 1-5 meses | F65: 6-11 meses | G65: 12-23 meses | H65: 24-59 meses
B66: Diarrea neonatal | C66: Exclusivo | D66: 1 | E66: 1 | F66: 1 | G66: 1 | H66: 1
C67: Predominante | D67: 1.35 | E67: 1 | F67: 1 | G67: 1 | H67: 1
C68: Parcial | D68: 1.35 | E68: 1 | F68: 1 | G68: 1 | H68: 1
C69: Ninguno | D69: 5.4 | E69: 1 | F69: 1 | G69: 1 | H69: 1
B70: Sepsis neonatal | C70: Exclusivo | D70: 1 | E70: 1 | F70: 1 | G70: 1 | H70: 1
C71: Predominante | D71: 1.35 | E71: 1 | F71: 1 | G71: 1 | H71: 1
C72: Parcial | D72: 1.35 | E72: 1 | F72: 1 | G72: 1 | H72: 1
C73: Ninguno | D73: 5.4 | E73: 1 | F73: 1 | G73: 1 | H73: 1
B74: Neumonía neonatal | C74: Exclusivo | D74: 1 | E74: 1 | F74: 1 | G74: 1 | H74: 1
C75: Predominante | D75: 1.35 | E75: 1 | F75: 1 | G75: 1 | H75: 1
C76: Parcial | D76: 1.35 | E76: 1 | F76: 1 | G76: 1 | H76: 1
C77: Ninguno | D77: 5.4 | E77: 1 | F77: 1 | G77: 1 | H77: 1
B78: Prematuridad neonatal | C78: Exclusivo | D78: 1 | E78: 1 | F78: 1 | G78: 1 | H78: 1
C79: Predominante | D79: 1 | E79: 1 | F79: 1 | G79: 1 | H79: 1
C80: Parcial | D80: 1 | E80: 1 | F80: 1 | G80: 1 | H80: 1
C81: Ninguno | D81: 1 | E81: 1 | F81: 1 | G81: 1 | H81: 1
B82: Diarrea | C82: Exclusivo | D82: 1 | E82: 1 | F82: 1 | G82: 1 | H82: 1
C83: Predominante | D83: 1 | E83: 2.28 | F83: 1 | G83: 1 | H83: 1
C84: Parcial | D84: 1 | E84: 4.62 | F84: 1 | G84: 1 | H84: 1
C85: Ninguno | D85: 1 | E85: 10.53 | F85: 1.47 | G85: 2.57 | H85: 1
B86: Neumonía | C86: Exclusivo | D86: 1 | E86: 1 | F86: 1 | G86: 1 | H86: 1
C87: Predominante | D87: 1 | E87: 1.66 | F87: 1 | G87: 1 | H87: 1
C88: Parcial | D88: 1 | E88: 2.5 | F88: 1 | G88: 1 | H88: 1
C89: Ninguno | D89: 1 | E89: 14.97 | F89: 1.92 | G89: 1.92 | H89: 1
B90: Sarampión | C90: Exclusivo | D90: 1 | E90: 1 | F90: 1 | G90: 1 | H90: 1
C91: Predominante | D91: 1 | E91: 1.48 | F91: 1 | G91: 1 | H91: 1
C92: Parcial | D92: 1 | E92: 2.84 | F92: 1 | G92: 1 | H92: 1
C93: Ninguno | D93: 1 | E93: 14.4 | F93: 3.69 | G93: 3.69 | H93: 1
B94: Meningitis | C94: Exclusivo | D94: 1 | E94: 1 | F94: 1 | G94: 1 | H94: 1
C95: Predominante | D95: 1 | E95: 1.48 | F95: 1 | G95: 1 | H95: 1
C96: Parcial | D96: 1 | E96: 2.84 | F96: 1 | G96: 1 | H96: 1
C97: Ninguno | D97: 1 | E97: 14.4 | F97: 3.69 | G97: 3.69 | H97: 1
B98: Tosferina | C98: Exclusivo | D98: 1 | E98: 1 | F98: 1 | G98: 1 | H98: 1
C99: Predominante | D99: 1 | E99: 1.48 | F99: 1 | G99: 1 | H99: 1
C100: Parcial | D100: 1 | E100: 2.84 | F100: 1 | G100: 1 | H100: 1
C101: Ninguno | D101: 1 | E101: 14.4 | F101: 3.69 | G101: 3.69 | H101: 1
A103: Riesgos relativos de sufrir diarrea según el estado de la lactancia materna
A104: Diarrea | B104: Ninguno | C104: Situación de lactancia materna | D104: <1 mes | E104: 1-5 meses | F104: 6-11 meses | G104: 12-23 meses | H104: 24-59 meses
...

Sheet Programas de anemia
C1: <1 mes | D1: 1-5 meses | E1: 6-11 meses | F1: 12-23 meses | G1: 24-59 meses | H1: WRA: 15-19 años (mujeres en edad reproductiva) | I1: WRA: 20-29 años (mujeres en edad reproductiva) | J1: WRA: 30-39 años (mujeres en edad reproductiva) | K1: WRA: 40-49 años (mujeres en edad reproductiva) | L1: PW: 15-19 años | M1: PW: 20-29 años | N1: PW: 30-39 años | O1: PW: 40-49 años
A2: Riesgos relativos de anemia cuando está cubierto por la intervención
B3: Retraso en el pinzamiento del cordón umbilical | C3: 0.92 | D3: 0.92 | E3: 0.92 | F3: 1 | G3: 1 | H3: 1 | I3: 1 | J3: 1 | K3: 1 | L3: 1 | M3: 1 | N3: 1 | O3: 1
B4: Suplementación con hierro y ácido fólico (comunidad) | C4: 1 | D4: 1 | E4: 1 | F4: 1 | G4: 1 | H4: 0.73 | I4: 0.73 | J4: 0.73 | K4: 0.73 | L4: 1 | M4: 1 | N4: 1 | O4: 1
B5: Suplementación con hierro y ácido fólico (centro de salud) | C5: 1 | D5: 1 | E5: 1 | F5: 1 | G5: 1 | H5: 0.73 | I5: 0.73 | J5: 0.73 | K5: 0.73 | L5: 1 | M5: 1 | N5: 1 | O5: 1
B6: Suplementación con hierro y ácido fólico (minorista) | C6: 1 | D6: 1 | E6: 1 | F6: 1 | G6: 1 | H6: 0.73 | I6: 0.73 | J6: 0.73 | K6: 0.73 | L6: 1 | M6: 1 | N6: 1 | O6: 1
B7: Suplementación con hierro y ácido fólico (escuela) | C7: 1 | D7: 1 | E7: 1 | F7: 1 | G7: 1 | H7: 0.73 | I7: 0.73 | J7: 0.73 | K7: 0.73 | L7: 1 | M7: 1 | N7: 1 | O7: 1
B8: Suplementación con hierro y ácido fólico para mujeres embarazadas (comunidad) | C8: 1 | D8: 1 | E8: 1 | F8: 1 | G8: 1 | H8: 1 | I8: 1 | J8: 1 | K8: 1 | L8: 0.51 | M8: 0.51 | N8: 0.51 | O8: 0.51
B9: Suplementación con hierro y ácido fólico para mujeres embarazadas (centro de salud) | C9: 1 | D9: 1 | E9: 1 | F9: 1 | G9: 1 | H9: 1 | I9: 1 | J9: 1 | K9: 1 | L9: 0.51 | M9: 0.51 | N9: 0.51 | O9: 0.51
B10: IPTp-Tratamiento preventivo intermitente de la malaria en el embarazo | C10: 1 | D10: 1 | E10: 1 | F10: 1 | G10: 1 | H10: 1 | I10: 1 | J10: 1 | K10: 1 | L10: 0.9 | M10: 0.9 | N10: 0.9 | O10: 0.9
B11: Suplementos nutricionales a base de lípidos | C11: 1 | D11: 1 | E11: 1 | F11: 1 | G11: 1 | H11: 1 | I11: 1 | J11: 1 | K11: 1 | L11: 1 | M11: 1 | N11: 1 | O11: 1
B12: Mosquiteros tratados con insecticida de larga duración | C12: 0.83 | D12: 0.83 | E12: 0.83 | F12: 0.83 | G12: 0.83 | H12: 0.83 | I12: 0.83 | J12: 0.83 | K12: 0.83 | L12: 0.83 | M12: 0.83 | N12: 0.83 | O12: 0.83
B13: Micronutrientes en polvo | C13: 1 | D13: 1 | E13: 0.69 | F13: 0.69 | G13: 0.69 | H13: 1 | I13: 1 | J13: 1 | K13: 1 | L13: 1 | M13: 1 | N13: 1 | O13: 1
B14: Suplementación con micronutrientes múltiples | C14: 1 | D14: 1 | E14: 1 | F14: 1 | G14: 1 | H14: 1 | I14: 1 | J14: 1 | K14: 1 | L14: =L8 -> 0.51 | M14: =M8 -> 0.51 | N14: =N8 -> 0.51 | O14: =O8 -> 0.51
B15: Suplementos nutricionales a base de lípidos en pequeñas cantidades | C15: 1 | D15: 1 | E15: 0.36 | F15: 0.36 | G15: 1 | H15: 1 | I15: 1 | J15: 1 | K15: 1 | L15: 1 | M15: 1 | N15: 1 | O15: 1
A17: Razón de momios de ser anémico cuando está cubierto por la intervención
B18: Enriquecimiento del maíz con hierro y ácido fólico | C18: 1 | D18: 1 | E18: 0.976 | F18: 0.976 | G18: 0.976 | H18: 0.976 | I18: 0.976 | J18: 0.976 | K18: 0.976 | L18: 0.976 | M18: 0.976 | N18: 0.976 | O18: 0.976
B19: Enriquecimiento del arroz con hierro y ácido fólico | C19: 1 | D19: 1 | E19: 0.976 | F19: 0.976 | G19: 0.976 | H19: 0.976 | I19: 0.976 | J19: 0.976 | K19: 0.976 | L19: 0.976 | M19: 0.976 | N19: 0.976 | O19: 0.976
B20: Enriquecimiento de la harina de trigo con hierro y ácido fólico | C20: 1 | D20: 1 | E20: 0.976 | F20: 0.976 | G20: 0.976 | H20: 0.976 | I20: 0.976 | J20: 0.976 | K20: 0.976 | L20: 0.976 | M20: 0.976 | N20: 0.976 | O20: 0.976
B21: Fortificación de la sal con hierro y yodo | C21: 1 | D21: 1 | E21: 0.976 | F21: 0.976 | G21: 0.976 | H21: 0.976 | I21: 0.976 | J21: 0.976 | K21: 0.976 | L21: 0.976 | M21: 0.976 | N21: 0.976 | O21: 0.976
A23: Límites inferiores
C24: <1 mes | D24: 1-5 meses | E24: 6-11 meses | F24: 12-23 meses | G24: 24-59 meses | H24: WRA: 15-19 años (mujeres en edad reproductiva) | I24: WRA: 20-29 años (mujeres en edad reproductiva) | J24: WRA: 30-39 años (mujeres en edad reproductiva) | K24: WRA: 40-49 años (mujeres en edad reproductiva) | L24: PW: 15-19 años | M24: PW: 20-29 años | N24: PW: 30-39 años | O24: PW: 40-49 años
A25: Riesgos relativos de anemia cuando está cubierto por la intervención - inferior
B26: Retraso en el pinzamiento del cordón umbilical | C26: 0.87 | D26: 0.87 | E26: 0.87 | F26: =IF(F3=1,1,F3*0.9) -> 1 | G26: =IF(G3=1,1,G3*0.9) -> 1 | H26: =IF(H3=1,1,H3*0.9) -> 1 | I26: =IF(I3=1,1,I3*0.9) -> 1 | J26: =IF(J3=1,1,J3*0.9) -> 1 | K26: =IF(K3=1,1,K3*0.9) -> 1 | L26: =IF(L3=1,1,L3*0.9) -> 1 | M26: =IF(M3=1,1,M3*0.9) -> 1 | ... O26: =IF(O3=1,1,O3*0.9) -> 1
B27: Suplementación con hierro y ácido fólico (comunidad) | C27: =IF(C4=1,1,C4*0.9) -> 1 | D27: =IF(D4=1,1,D4*0.9) -> 1 | E27: =IF(E4=1,1,E4*0.9) -> 1 | F27: =IF(F4=1,1,F4*0.9) -> 1 | G27: =IF(G4=1,1,G4*0.9) -> 1 | H27: 0.56 | I27: 0.56 | J27: 0.56 | K27: 0.56 | L27: =IF(L4=1,1,L4*0.9) -> 1 | M27: =IF(M4=1,1,M4*0.9) -> 1 | N27: =IF(N4=1,1,N4*0.9) -> 1 | O27: =IF(O4=1,1,O4*0.9) -> 1
B28: Suplementación con hierro y ácido fólico (centro de salud) | C28: =IF(C5=1,1,C5*0.9) -> 1 | D28: =IF(D5=1,1,D5*0.9) -> 1 | E28: =IF(E5=1,1,E5*0.9) -> 1 | F28: =IF(F5=1,1,F5*0.9) -> 1 | G28: =IF(G5=1,1,G5*0.9) -> 1 | H28: 0.56 | I28: 0.56 | J28: 0.56 | K28: 0.56 | L28: =IF(L5=1,1,L5*0.9) -> 1 | M28: =IF(M5=1,1,M5*0.9) -> 1 | N28: =IF(N5=1,1,N5*0.9) -> 1 | O28: =IF(O5=1,1,O5*0.9) -> 1
B29: Suplementación con hierro y ácido fólico (minorista) | C29: =IF(C6=1,1,C6*0.9) -> 1 | D29: =IF(D6=1,1,D6*0.9) -> 1 | E29: =IF(E6=1,1,E6*0.9) -> 1 | F29: =IF(F6=1,1,F6*0.9) -> 1 | G29: =IF(G6=1,1,G6*0.9) -> 1 | H29: 0.56 | I29: 0.56 | J29: 0.56 | K29: 0.56 | L29: =IF(L6=1,1,L6*0.9) -> 1 | M29: =IF(M6=1,1,M6*0.9) -> 1 | N29: =IF(N6=1,1,N6*0.9) -> 1 | O29: =IF(O6=1,1,O6*0.9) -> 1
B30: Suplementación con hierro y ácido fólico (escuela) | C30: =IF(C7=1,1,C7*0.9) -> 1 | D30: =IF(D7=1,1,D7*0.9) -> 1 | E30: =IF(E7=1,1,E7*0.9) -> 1 | F30: =IF(F7=1,1,F7*0.9) -> 1 | G30: =IF(G7=1,1,G7*0.9) -> 1 | H30: 0.56 | I30: 0.56 | J30: 0.56 | K30: 0.56 | L30: =IF(L7=1,1,L7*0.9) -> 1 | M30: =IF(M7=1,1,M7*0.9) -> 1 | N30: =IF(N7=1,1,N7*0.9) -> 1 | O30: =IF(O7=1,1,O7*0.9) -> 1
B31: Suplementación con hierro y ácido fólico para mujeres embarazadas (comunidad) | C31: =IF(C8=1,1,C8*0.9) -> 1 | D31: =IF(D8=1,1,D8*0.9) -> 1 | E31: =IF(E8=1,1,E8*0.9) -> 1 | F31: =IF(F8=1,1,F8*0.9) -> 1 | G31: =IF(G8=1,1,G8*0.9) -> 1 | H31: =IF(H8=1,1,H8*0.9) -> 1 | I31: =IF(I8=1,1,I8*0.9) -> 1 | J31: =IF(J8=1,1,J8*0.9) -> 1 | K31: =IF(K8=1,1,K8*0.9) -> 1 | L31: 0.38 | M31: 0.38 | N31: 0.38 | O31: 0.38
B32: Suplementación con hierro y ácido fólico para mujeres embarazadas (centro de salud) | C32: =IF(C9=1,1,C9*0.9) -> 1 | D32: =IF(D9=1,1,D9*0.9) -> 1 | E32: =IF(E9=1,1,E9*0.9) -> 1 | F32: =IF(F9=1,1,F9*0.9) -> 1 | G32: =IF(G9=1,1,G9*0.9) -> 1 | H32: =IF(H9=1,1,H9*0.9) -> 1 | I32: =IF(I9=1,1,I9*0.9) -> 1 | J32: =IF(J9=1,1,J9*0.9) -> 1 | K32: =IF(K9=1,1,K9*0.9) -> 1 | L32: 0.38 | M32: 0.38 | N32: 0.38 | O32: 0.38
B33: IPTp-Tratamiento preventivo intermitente de la malaria en el embarazo | C33: =IF(C10=1,1,C10*0.9) -> 1 | D33: =IF(D10=1,1,D10*0.9) -> 1 | E33: =IF(E10=1,1,E10*0.9) -> 1 | F33: =IF(F10=1,1,F10*0.9) -> 1 | G33: =IF(G10=1,1,G10*0.9) -> 1 | H33: =IF(H10=1,1,H10*0.9) -> 1 | I33: =IF(I10=1,1,I10*0.9) -> 1 | J33: =IF(J10=1,1,J10*0.9) -> 1 | K33: =IF(K10=1,1,K10*0.9) -> 1 | L33: 0.74 | M33: 0.74 | N33: 0.74 | O33: 0.74
B34: Suplementos nutricionales a base de lípidos | C34: =IF(C11=1,1,C11*0.9) -> 1 | D34: =IF(D11=1,1,D11*0.9) -> 1 | E34: =IF(E11=1,1,E11*0.9) -> 1 | F34: =IF(F11=1,1,F11*0.9) -> 1 | G34: 1 | H34: =IF(H11=1,1,H11*0.9) -> 1 | I34: =IF(I11=1,1,I11*0.9) -> 1 | J34: =IF(J11=1,1,J11*0.9) -> 1 | K34: =IF(K11=1,1,K11*0.9) -> 1 | L34: =IF(L11=1,1,L11*0.9) -> 1 | M34: =IF(M11=1,1,M11*0.9) -> 1 | N34: =IF(N11=1,1,N11*0.9) -> 1 | O34: =IF(O11=1,1,O11*0.9) -> 1
B35: Mosquiteros tratados con insecticida de larga duración | C35: 0.74 | D35: 0.74 | E35: 0.74 | F35: 0.74 | G35: 0.74 | H35: 0.74 | I35: 0.74 | J35: 0.74 | K35: 0.74 | L35: 0.74 | M35: 0.74 | N35: 0.74 | O35: 0.74
B36: Micronutrientes en polvo | C36: =IF(C13=1,1,C13*0.9) -> 1 | D36: =IF(D13=1,1,D13*0.9) -> 1 | E36: 0.62 | F36: 0.62 | G36: 0.62 | H36: =IF(H13=1,1,H13*0.9) -> 1 | I36: =IF(I13=1,1,I13*0.9) -> 1 | J36: =IF(J13=1,1,J13*0.9) -> 1 | K36: =IF(K13=1,1,K13*0.9) -> 1 | L36: =IF(L13=1,1,L13*0.9) -> 1 | M36: =IF(M13=1,1,M13*0.9) -> 1 | N36: =IF(N13=1,1,N13*0.9) -> 1 | O36: =IF(O13=1,1,O13*0.9) -> 1
B37: Suplementación con micronutrientes múltiples | C37: =IF(C14=1,1,C14*0.9) -> 1 | D37: =IF(D14=1,1,D14*0.9) -> 1 | E37: =IF(E14=1,1,E14*0.9) -> 1 | F37: =IF(F14=1,1,F14*0.9) -> 1 | G37: =IF(G14=1,1,G14*0.9) -> 1 | H37: =IF(H14=1,1,H14*0.9) -> 1 | I37: =IF(I14=1,1,I14*0.9) -> 1 | J37: =IF(J14=1,1,J14*0.9) -> 1 | K37: =IF(K14=1,1,K14*0.9) -> 1 | L37: 1 | M37: 1 | N37: 1 | O37: 1
B38: Suplementos nutricionales a base de lípidos en pequeñas cantidades | C38: =IF(C15=1,1,C15*0.9) -> 1 | D38: =IF(D15=1,1,D15*0.9) -> 1 | E38: 0.3 | F38: 0.3 | G38: =IF(G15=1,1,G15*0.9) -> 1 | H38: =IF(H15=1,1,H15*0.9) -> 1 | I38: =IF(I15=1,1,I15*0.9) -> 1 | J38: =IF(J15=1,1,J15*0.9) -> 1 | K38: =IF(K15=1,1,K15*0.9) -> 1 | L38: =IF(L15=1,1,L15*0.9) -> 1 | M38: =IF(M15=1,1,M15*0.9) -> 1 | N38: =IF(N15=1,1,N15*0.9) -> 1 | O38: =IF(O15=1,1,O15*0.9) -> 1
A40: Razón de momios de ser anémico cuando está cubierto por la intervención-menor
B41: Enriquecimiento del maíz con hierro y ácido fólico | C41: =IF(C18=1,1,C18*0.9) -> 1 | D41: =IF(D18=1,1,D18*0.9) -> 1 | E41: 0.975 | F41: 0.975 | G41: 0.975 | H41: 0.975 | I41: 0.975 | J41: 0.975 | K41: 0.975 | L41: 0.975 | M41: 0.975 | N41: 0.975 | O41: 0.975
B42: Enriquecimiento del arroz con hierro y ácido fólico | C42: =IF(C19=1,1,C19*0.9) -> 1 | D42: =IF(D19=1,1,D19*0.9) -> 1 | E42: 0.975 | F42: 0.975 | G42: 0.975 | H42: 0.975 | I42: 0.975 | J42: 0.975 | K42: 0.975 | L42: 0.975 | M42: 0.975 | N42: 0.975 | O42: 0.975
B43: Enriquecimiento de la harina de trigo con hierro y ácido fólico | C43: =IF(C20=1,1,C20*0.9) -> 1 | D43: =IF(D20=1,1,D20*0.9) -> 1 | E43: 0.975 | F43: 0.975 | G43: 0.975 | H43: 0.975 | I43: 0.975 | J43: 0.975 | K43: 0.975 | L43: 0.975 | M43: 0.975 | N43: 0.975 | O43: 0.975
B44: Fortificación de la sal con hierro y yodo | C44: =IF(C21=1,1,C21*0.9) -> 1 | D44: =IF(D21=1,1,D21*0.9) -> 1 | E44: 0.975 | F44: 0.975 | G44: 0.975 | H44: 0.975 | I44: 0.975 | J44: 0.975 | K44: 0.975 | L44: 0.975 | M44: 0.975 | N44: 0.975 | O44: 0.975
A46: Límites superiores
C47: <1 mes | D47: 1-5 meses | E47: 6-11 meses | F47: 12-23 meses | G47: 24-59 meses | H47: WRA: 15-19 años (mujeres en edad reproductiva) | I47: WRA: 20-29 años (mujeres en edad reproductiva) | J47: WRA: 30-39 años (mujeres en edad reproductiva) | K47: WRA: 40-49 años (mujeres en edad reproductiva) | L47: PW: 15-19 años | M47: PW: 20-29 años | N47: PW: 30-39 años | O47: PW: 40-49 años
A48: Riesgos relativos de anemia cuando está cubierto por la intervención - superior
B49: Retraso en el pinzamiento del cordón umbilical | C49: 0.99 | D49: 0.99 | E49: 0.99 | F49: =IF(F3=1,1,F3*1.05) -> 1 | G49: =IF(G3=1,1,G3*1.05) -> 1 | H49: =IF(H3=1,1,H3*1.05) -> 1 | I49: =IF(I3=1,1,I3*1.05) -> 1 | J49: =IF(J3=1,1,J3*1.05) -> 1 | K49: =IF(K3=1,1,K3*1.05) -> 1 | L49: =IF(L3=1,1,L3*1.05) -> 1 | M49: =IF(M3=1,1,M3*1.05) -> 1 | ... O49: =IF(O3=1,1,O3*1.05) -> 1
B50: Suplementación con hierro y ácido fólico (comunidad) | C50: =IF(C4=1,1,C4*1.05) -> 1 | D50: =IF(D4=1,1,D4*1.05) -> 1 | E50: =IF(E4=1,1,E4*1.05) -> 1 | F50: =IF(F4=1,1,F4*1.05) -> 1 | G50: =IF(G4=1,1,G4*1.05) -> 1 | H50: 0.95 | I50: 0.95 | J50: 0.95 | K50: 0.95 | L50: =IF(L4=1,1,L4*1.05) -> 1 | M50: =IF(M4=1,1,M4*1.05) -> 1 | N50: =IF(N4=1,1,N4*1.05) -> 1 | O50: =IF(O4=1,1,O4*1.05) -> 1
B51: Suplementación con hierro y ácido fólico (centro de salud) | C51: =IF(C5=1,1,C5*1.05) -> 1 | D51: =IF(D5=1,1,D5*1.05) -> 1 | E51: =IF(E5=1,1,E5*1.05) -> 1 | F51: =IF(F5=1,1,F5*1.05) -> 1 | G51: =IF(G5=1,1,G5*1.05) -> 1 | H51: 0.95 | I51: 0.95 | J51: 0.95 | K51: 0.95 | L51: =IF(L5=1,1,L5*1.05) -> 1 | M51: =IF(M5=1,1,M5*1.05) -> 1 | N51: =IF(N5=1,1,N5*1.05) -> 1 | O51: =IF(O5=1,1,O5*1.05) -> 1
B52: Suplementación con hierro y ácido fólico (minorista) | C52: =IF(C6=1,1,C6*1.05) -> 1 | D52: =IF(D6=1,1,D6*1.05) -> 1 | E52: =IF(E6=1,1,E6*1.05) -> 1 | F52: =IF(F6=1,1,F6*1.05) -> 1 | G52: =IF(G6=1,1,G6*1.05) -> 1 | H52: 0.95 | I52: 0.95 | J52: 0.95 | K52: 0.95 | L52: =IF(L6=1,1,L6*1.05) -> 1 | M52: =IF(M6=1,1,M6*1.05) -> 1 | N52: =IF(N6=1,1,N6*1.05) -> 1 | O52: =IF(O6=1,1,O6*1.05) -> 1
B53: Suplementación con hierro y ácido fólico (escuela) | C53: =IF(C7=1,1,C7*1.05) -> 1 | D53: =IF(D7=1,1,D7*1.05) -> 1 | E53: =IF(E7=1,1,E7*1.05) -> 1 | F53: =IF(F7=1,1,F7*1.05) -> 1 | G53: =IF(G7=1,1,G7*1.05) -> 1 | H53: 0.95 | I53: 0.95 | J53: 0.95 | K53: 0.95 | L53: =IF(L7=1,1,L7*1.05) -> 1 | M53: =IF(M7=1,1,M7*1.05) -> 1 | N53: =IF(N7=1,1,N7*1.05) -> 1 | O53: =IF(O7=1,1,O7*1.05) -> 1
B54: Suplementación con hierro y ácido fólico para mujeres embarazadas (comunidad) | C54: =IF(C8=1,1,C8*1.05) -> 1 | D54: =IF(D8=1,1,D8*1.05) -> 1 | E54: =IF(E8=1,1,E8*1.05) -> 1 | F54: =IF(F8=1,1,F8*1.05) -> 1 | G54: =IF(G8=1,1,G8*1.05) -> 1 | H54: =IF(H8=1,1,H8*1.05) -> 1 | I54: =IF(I8=1,1,I8*1.05) -> 1 | J54: =IF(J8=1,1,J8*1.05) -> 1 | K54: =IF(K8=1,1,K8*1.05) -> 1 | L54: 0.7 | M54: 0.7 | N54: 0.7 | O54: 0.7
B55: Suplementación con hierro y ácido fólico para mujeres embarazadas (centro de salud) | C55: =IF(C9=1,1,C9*1.05) -> 1 | D55: =IF(D9=1,1,D9*1.05) -> 1 | E55: =IF(E9=1,1,E9*1.05) -> 1 | F55: =IF(F9=1,1,F9*1.05) -> 1 | G55: =IF(G9=1,1,G9*1.05) -> 1 | H55: =IF(H9=1,1,H9*1.05) -> 1 | I55: =IF(I9=1,1,I9*1.05) -> 1 | J55: =IF(J9=1,1,J9*1.05) -> 1 | K55: =IF(K9=1,1,K9*1.05) -> 1 | L55: 0.7 | M55: 0.7 | N55: 0.7 | O55: 0.7
B56: IPTp-Tratamiento preventivo intermitente de la malaria en el embarazo | C56: =IF(C10=1,1,C10*1.05) -> 1 | D56: =IF(D10=1,1,D10*1.05) -> 1 | E56: =IF(E10=1,1,E10*1.05) -> 1 | F56: =IF(F10=1,1,F10*1.05) -> 1 | G56: =IF(G10=1,1,G10*1.05) -> 1 | H56: =IF(H10=1,1,H10*1.05) -> 1 | I56: =IF(I10=1,1,I10*1.05) -> 1 | J56: =IF(J10=1,1,J10*1.05) -> 1 | K56: =IF(K10=1,1,K10*1.05) -> 1 | L56: 0.95 | M56: 0.95 | N56: 0.95 | O56: 0.95
B57: Suplementos nutricionales a base de lípidos | C57: =IF(C11=1,1,C11*1.05) -> 1 | D57: =IF(D11=1,1,D11*1.05) -> 1 | E57: =IF(E11=1,1,E11*1.05) -> 1 | F57: =IF(F11=1,1,F11*1.05) -> 1 | G57: =IF(G11=1,1,G11*1.05) -> 1 | H57: =IF(H11=1,1,H11*1.05) -> 1 | I57: =IF(I11=1,1,I11*1.05) -> 1 | J57: =IF(J11=1,1,J11*1.05) -> 1 | ... O57: =IF(O11=1,1,O11*1.05) -> 1
B58: Mosquiteros tratados con insecticida de larga duración | C58: 0.93 | D58: 0.93 | E58: 0.93 | F58: 0.93 | G58: 0.93 | H58: 0.93 | I58: 0.93 | J58: 0.93 | K58: 0.93 | L58: 0.93 | M58: 0.93 | N58: 0.93 | O58: 0.93
B59: Micronutrientes en polvo | C59: =IF(C13=1,1,C13*1.05) -> 1 | D59: =IF(D13=1,1,D13*1.05) -> 1 | E59: 0.77 | F59: 0.77 | G59: 0.77 | H59: =IF(H13=1,1,H13*1.05) -> 1 | I59: =IF(I13=1,1,I13*1.05) -> 1 | J59: =IF(J13=1,1,J13*1.05) -> 1 | K59: =IF(K13=1,1,K13*1.05) -> 1 | L59: =IF(L13=1,1,L13*1.05) -> 1 | M59: =IF(M13=1,1,M13*1.05) -> 1 | N59: =IF(N13=1,1,N13*1.05) -> 1 | O59: =IF(O13=1,1,O13*1.05) -> 1
B60: Suplementación con micronutrientes múltiples | C60: =IF(C14=1,1,C14*1.05) -> 1 | D60: =IF(D14=1,1,D14*1.05) -> 1 | E60: =IF(E14=1,1,E14*1.05) -> 1 | F60: =IF(F14=1,1,F14*1.05) -> 1 | G60: =IF(G14=1,1,G14*1.05) -> 1 | H60: =IF(H14=1,1,H14*1.05) -> 1 | I60: =IF(I14=1,1,I14*1.05) -> 1 | J60: =IF(J14=1,1,J14*1.05) -> 1 | K60: =IF(K14=1,1,K14*1.05) -> 1 | L60: 1 | M60: 1 | N60: 1 | O60: 1
B61: Suplementos nutricionales a base de lípidos en pequeñas cantidades | C61: =IF(C15=1,1,C15*1.05) -> 1 | D61: =IF(D15=1,1,D15*1.05) -> 1 | E61: 0.44 | F61: 0.44 | G61: =IF(G15=1,1,G15*1.05) -> 1 | H61: =IF(H15=1,1,H15*1.05) -> 1 | I61: =IF(I15=1,1,I15*1.05) -> 1 | J61: =IF(J15=1,1,J15*1.05) -> 1 | K61: =IF(K15=1,1,K15*1.05) -> 1 | L61: =IF(L15=1,1,L15*1.05) -> 1 | M61: =IF(M15=1,1,M15*1.05) -> 1 | N61: =IF(N15=1,1,N15*1.05) -> 1 | O61: =IF(O15=1,1,O15*1.05) -> 1
A63: Razón de momios de ser anémico cuando está cubierto por la intervención - superior
B64: Enriquecimiento del maíz con hierro y ácido fólico | C64: =IF(C18=1,1,C18*1.05) -> 1 | D64: =IF(D18=1,1,D18*1.05) -> 1 | E64: 0.978 | F64: 0.978 | G64: 0.978 | H64: 0.978 | I64: 0.978 | J64: 0.978 | K64: 0.978 | L64: 0.978 | M64: 0.978 | N64: 0.978 | O64: 0.978
B65: Enriquecimiento del arroz con hierro y ácido fólico | C65: =IF(C19=1,1,C19*1.05) -> 1 | D65: =IF(D19=1,1,D19*1.05) -> 1 | E65: 0.978 | F65: 0.978 | G65: 0.978 | H65: 0.978 | I65: 0.978 | J65: 0.978 | K65: 0.978 | L65: 0.978 | M65: 0.978 | N65: 0.978 | O65: 0.978
B66: Enriquecimiento de la harina de trigo con hierro y ácido fólico | C66: =IF(C20=1,1,C20*1.05) -> 1 | D66: =IF(D20=1,1,D20*1.05) -> 1 | E66: 0.978 | F66: 0.978 | G66: 0.978 | H66: 0.978 | I66: 0.978 | J66: 0.978 | K66: 0.978 | L66: 0.978 | M66: 0.978 | N66: 0.978 | O66: 0.978
B67: Fortificación de la sal con hierro y yodo | C67: =IF(C21=1,1,C21*1.05) -> 1 | D67: =IF(D21=1,1,D21*1.05) -> 1 | E67: 0.978 | F67: 0.978 | G67: 0.978 | H67: 0.978 | I67: 0.978 | J67: 0.978 | K67: 0.978 | L67: 0.978 | M67: 0.978 | N67: 0.978 | O67: 0.978

Sheet Programas para emaciación
C1: <1 mes | D1: 1-5 meses | E1: 6-11 meses | F1: 12-23 meses | G1: 24-59 meses
A2: Razón de momios de MAS cuando está cubierto por el programa
B3: Tratamiento de la MAS | C3: 1 | D3: =1/1.33 -> 0.7518797 | E3: =1/1.33 -> 0.7518797 | F3: =1/1.33 -> 0.7518797 | G3: =1/1.33 -> 0.7518797
A4: Razón de momios de MAM cuando está cubierto por el programa
B5: Manejo de la Malnutrición Aguda Moderada (MAM) | C5: 1 | D5: =1/1.33 -> 0.7518797 | E5: =1/1.33 -> 0.7518797 | F5: =1/1.33 -> 0.7518797 | G5: =1/1.33 -> 0.7518797
A7: Límite inferior
C8: <1 mes | D8: 1-5 meses | E8: 6-11 meses | F8: 12-23 meses | G8: 24-59 meses
A9: Razón de momios de MAS cuando está cubierto por el programa - inferior
B10: Tratamiento de la MAS | C10: 1 | D10: =1/1.54 -> 0.64935065 | E10: =1/1.54 -> 0.64935065 | F10: =1/1.54 -> 0.64935065 | G10: =1/1.54 -> 0.64935065
A11: Razón de momios de MAM cuando está cubierto por el programa - inferior
B12: Manejo de la Malnutrición Aguda Moderada (MAM) | C12: 1 | D12: =1/1.54 -> 0.64935065 | E12: =1/1.54 -> 0.64935065 | F12: =1/1.54 -> 0.64935065 | G12: =1/1.54 -> 0.64935065
A14: Límite superior
C15: <1 mes | D15: 1-5 meses | E15: 6-11 meses | F15: 12-23 meses | G15: 24-59 meses
A16: Razón de momios de MAS cuando está cubierto por el programa - superior
B17: Tratamiento de la MAS | C17: 1 | D17: =1/1.16 -> 0.86206897 | E17: =1/1.16 -> 0.86206897 | F17: =1/1.16 -> 0.86206897 | G17: =1/1.16 -> 0.86206897
A18: Razón de momios de MAM cuando está cubierto por el programaa - superior
B19: Manejo de la Malnutrición Aguda Moderada (MAM) | C19: 1 | D19: =1/1.16 -> 0.86206897 | E19: =1/1.16 -> 0.86206897 | F19: =1/1.16 -> 0.86206897 | G19: =1/1.16 -> 0.86206897

Sheet Programas para niños
A1: Programa | B1: Condición objetivo | C1: Outcome | D1: <1 mes | E1: 1-5 meses | F1: 6-11 meses | G1: 12-23 meses | H1: 24-59 meses
A2: Suplementación con vitamina A | B2: Diarrea | C2: Fracción afectada | D2: 0 | E2: 0 | F2: 1 | G2: 1 | H2: 1
C3: Efectividad en mortalidad | D3: 0 | E3: 0 | F3: 0.12 | G3: 0.12 | H3: 0.12
C4: Efectividad en incidencia | D4: 0 | E4: 0 | F4: 0.15 | G4: 0.15 | H4: 0.15
A5: Suministro público de alimentos complementarios | B5: MAS | C5: Fracción afectada | D5: 0 | E5: 0 | F5: 1 | G5: 1 | H5: 0
C6: Efectividad en incidencia | D6: 0 | E6: 0 | F6: 0 | G6: 0 | H6: 0
B7: MAM | C7: Fracción afectada | D7: 0 | E7: 0 | F7: 1 | G7: 1 | H7: 0
C8: Efectividad en incidencia | D8: 0 | E8: 0 | F8: 0 | G8: 0 | H8: 0
A9: Suplementos nutricionales a base de lípidos | B9: MAS | C9: Fracción afectada | D9: 0 | E9: 0 | F9: 1 | G9: 1 | H9: 0
C10: Efectividad en incidencia | D10: 0 | E10: 0 | F10: 0 | G10: 0 | H10: 0
B11: MAM | C11: Fracción afectada | D11: 0 | E11: 0 | F11: 1 | G11: 1 | H11: 0
C12: Efectividad en incidencia | D12: 0 | E12: 0 | F12: 0 | G12: 0 | H12: 0
A13: Suplementos nutricionales a base de lípidos en pequeñas cantidades | B13: MAS | C13: Fracción afectada | D13: 0 | E13: 0 | F13: 1 | G13: 1 | H13: 0
C14: Efectividad en incidencia | D14: 0 | E14: 0 | F14: 0.31 | G14: 0.31 | H14: 0
B15: MAM | C15: Fracción afectada | D15: 0 | E15: 0 | F15: 1 | G15: 1 | H15: 0
C16: Efectividad en incidencia | D16: 0 | E16: 0 | F16: 0.14 | G16: 0.14 | H16: 0
A17: Transferencias de efectivo | B17: MAS | C17: Fracción afectada | D17: 0 | E17: 0 | F17: 1 | G17: 1 | H17: 1
C18: Efectividad en incidencia | D18: 0 | E18: 0 | F18: 0 | G18: 0 | H18: 0
B19: MAM | C19: Fracción afectada | D19: 0 | E19: 0 | F19: 1 | G19: 1 | H19: 1
C20: Efectividad en incidencia | D20: 0 | E20: 0 | F20: 0 | G20: 0 | H20: 0
A21: Enriquecimiento de la harina de trigo con hierro y ácido fólico | B21: Anomalías congénitas neonatales | C21: Fracción afectada | D21: 1 | E21: 0 | F21: 0 | G21: 0 | H21: 0
C22: Efectividad en mortalidad | D22: 0.13 | E22: 0 | F22: 0 | G22: 0 | H22: 0
A23: Enriquecimiento del maíz con hierro y ácido fólico | B23: Anomalías congénitas neonatales | C23: Fracción afectada | D23: 1 | E23: 0 | F23: 0 | G23: 0 | H23: 0
C24: Efectividad en mortalidad | D24: 0.13 | E24: 0 | F24: 0 | G24: 0 | H24: 0
A25: Enriquecimiento del arroz con hierro y ácido fólico | B25: Anomalías congénitas neonatales | C25: Fracción afectada | D25: 1 | E25: 0 | F25: 0 | G25: 0 | H25: 0
C26: Efectividad en mortalidad | D26: 0.13 | E26: 0 | F26: 0 | G26: 0 | H26: 0
A27: WASH: Mejora de la fuente de agua | B27: Diarrea | C27: Fracción afectada | D27: 1 | E27: 1 | F27: 1 | G27: 1 | H27: 1
C28: Efectividad en mortalidad | D28: 0.3 | E28: 0.3 | F28: 0.3 | G28: 0.3 | H28: 0.3
C29: Efectividad en incidencia | D29: 0 | E29: 0 | F29: 0 | G29: 0 | H29: 0
A30: WASH: Agua corriente o entubada | B30: Diarrea | C30: Fracción afectada | D30: 1 | E30: 1 | F30: 1 | G30: 1 | H30: 1
C31: Efectividad en mortalidad | D31: 0 | E31: 0 | F31: 0 | G31: 0 | H31: 0
C32: Efectividad en incidencia | D32: 0 | E32: 0 | F32: 0 | G32: 0 | H32: 0
A33: WASH: Mejora del saneamiento | B33: Diarrea | C33: Fracción afectada | D33: 1 | E33: 1 | F33: 1 | G33: 1 | H33: 1
C34: Efectividad en mortalidad | D34: 0 | E34: 0 | F34: 0 | G34: 0 | H34: 0
C35: Efectividad en incidencia | D35: 0 | E35: 0 | F35: 0 | G35: 0 | H35: 0
A36: WASH: Eliminación higiénica de residuos | B36: Diarrea | C36: Fracción afectada | D36: 1 | E36: 1 | F36: 1 | G36: 1 | H36: 1
C37: Efectividad en mortalidad | D37: 0 | E37: 0 | F37: 0 | G37: 0 | H37: 0
C38: Efectividad en incidencia | D38: 0 | E38: 0 | F38: 0 | G38: 0 | H38: 0
A39: WASH: Lavado de manos | B39: Diarrea | C39: Fracción afectada | D39: 1 | E39: 1 | F39: 1 | G39: 1 | H39: 1
C40: Efectividad en mortalidad | D40: 0 | E40: 0 | F40: 0 | G40: 0 | H40: 0
C41: Efectividad en incidencia | D41: 0 | E41: 0 | F41: 0 | G41: 0 | H41: 0
A42: Suplementación con zinc | B42: Diarrea | C42: Fracción afectada | D42: 0 | E42: 1 | F42: 1 | G42: 1 | H42: 1
C43: Efectividad en mortalidad | D43: 0 | E43: 0 | F43: 0 | G43: 0 | H43: 0
C44: Efectividad en incidencia | D44: 0.09 | E44: 0.09 | F44: 0.09 | G44: 0.09 | H44: 0.09
B45: Neumonía | C45: Fracción afectada | D45: 0 | E45: 1 | F45: 1 | G45: 1 | H45: 1
C46: Efectividad en mortalidad | D46: 0 | E46: 0 | F46: 0 | G46: 0 | H46: 0
C47: Efectividad en incidencia | D47: 0 | E47: 0 | F47: 0 | G47: 0 | H47: 0
A48: Sales de rehidratación oral | B48: Diarrea | C48: Fracción afectada | D48: 1 | E48: 1 | F48: 1 | G48: 1 | H48: 1
C49: Efectividad en mortalidad | D49: 0.69 | E49: 0.69 | F49: 0.69 | G49: 0.69 | H49: 0.69
A50: Zinc para el tratamiento + SRO | B50: Diarrea | C50: Fracción afectada | D50: 1 | E50: 1 | F50: 1 | G50: 1 | H50: 1
C51: Efectividad en mortalidad | D51: 0.76 | E51: 0.76 | F51: 0.76 | G51: 0.76 | H51: 0.76
A52: Método de la madre canguro | B52: Prematuridad neonatal | C52: Fracción afectada | D52: 1 | E52: 0 | F52: 0 | G52: 0 | H52: 0
C53: Efectividad en mortalidad | D53: 0.32 | E53: 0 | F53: 0 | G53: 0 | H53: 0
A55: Límite inferior
A56: Programa | B56: Condición objetivo | C56: Outcome | D56: <1 mes | E56: 1-5 meses | F56: 6-11 meses | G56: 12-23 meses | H56: 24-59 meses
A57: Suplementación con vitamina A | B57: Diarrea | C57: Fracción afectada | D57: =IF($C2="Affected fraction",D2,IF(D2=1,1,D2*0.9)) -> 0 | E57: =IF($C2="Affected fraction",E2,IF(E2=1,1,E2*0.9)) -> 0 | F57: =IF($C2="Affected fraction",F2,IF(F2=1,1,F2*0.9)) -> 1 | G57: =IF($C2="Affected fraction",G2,IF(G2=1,1,G2*0.9)) -> 1 | H57: =IF($C2="Affected fraction",H2,IF(H2=1,1,H2*0.9)) -> 1
C58: Efectividad en mortalidad | D58: =IF($C3="Affected fraction",D3,IF(D3=1,1,D3*0.9)) -> 0 | E58: =IF($C3="Affected fraction",E3,IF(E3=1,1,E3*0.9)) -> 0 | F58: 0.02 | G58: 0.02 | H58: 0.02
C59: Efectividad en incidencia | D59: =IF($C4="Affected fraction",D4,IF(D4=1,1,D4*0.9)) -> 0 | E59: =IF($C4="Affected fraction",E4,IF(E4=1,1,E4*0.9)) -> 0 | F59: 0.13 | G59: 0.13 | H59: 0.13
A60: Suministro público de alimentos complementarios | B60: MAS | C60: Fracción afectada | D60: 0 | E60: 0 | F60: 1 | G60: 1 | H60: 0
C61: Efectividad en incidencia | D61: 0 | E61: 0 | F61: 0 | G61: 0 | H61: 0
B62: MAM | C62: Fracción afectada | D62: 0 | E62: 0 | F62: 1 | G62: 1 | H62: 0
C63: Efectividad en incidencia | D63: 0 | E63: 0 | F63: 0 | G63: 0 | H63: 0
A64: Suplementos nutricionales a base de lípidos | B64: MAS | C64: Fracción afectada | D64: 0 | E64: 0 | F64: 1 | G64: 1 | H64: 0
C65: Efectividad en incidencia | D65: 0 | E65: 0 | F65: 0 | G65: 0 | H65: 0
B66: MAM | C66: Fracción afectada | D66: 0 | E66: 0 | F66: 1 | G66: 1 | H66: 0
C67: Efectividad en incidencia | D67: 0 | E67: 0 | F67: 0 | G67: 0 | H67: 0
A68: Suplementos nutricionales a base de lípidos en pequeñas cantidades | B68: MAS | C68: Fracción afectada | D68: 0 | E68: 0 | F68: 1 | G68: 1 | H68: 0
C69: Efectividad en incidencia | D69: =IF($C14="Affected fraction",D14,IF(D14=1,1,D14*0.9)) -> 0 | E69: =IF($C14="Affected fraction",E14,IF(E14=1,1,E14*0.9)) -> 0 | F69: 0.14 | G69: 0.14 | H69: =IF($C14="Affected fraction",H14,IF(H14=1,1,H14*0.9)) -> 0
B70: MAM | C70: Fracción afectada | D70: =IF($C15="Affected fraction",D15,IF(D15=1,1,D15*0.9)) -> 0 | E70: =IF($C15="Affected fraction",E15,IF(E15=1,1,E15*0.9)) -> 0 | F70: =IF($C15="Affected fraction",F15,IF(F15=1,1,F15*0.9)) -> 1 | G70: =IF($C15="Affected fraction",G15,IF(G15=1,1,G15*0.9)) -> 1 | H70: =IF($C15="Affected fraction",H15,IF(H15=1,1,H15*0.9)) -> 0
C71: Efectividad en incidencia | D71: =IF($C16="Affected fraction",D16,IF(D16=1,1,D16*0.9)) -> 0 | E71: =IF($C16="Affected fraction",E16,IF(E16=1,1,E16*0.9)) -> 0 | F71: 0 | G71: 0 | H71: =IF($C16="Affected fraction",H16,IF(H16=1,1,H16*0.9)) -> 0
A72: Transferencias de efectivo | B72: MAS | C72: Fracción afectada | D72: =IF($C17="Affected fraction",D17,IF(D17=1,1,D17*0.9)) -> 0 | E72: =IF($C17="Affected fraction",E17,IF(E17=1,1,E17*0.9)) -> 0 | F72: =IF($C17="Affected fraction",F17,IF(F17=1,1,F17*0.9)) -> 1 | G72: =IF($C17="Affected fraction",G17,IF(G17=1,1,G17*0.9)) -> 1 | H72: =IF($C17="Affected fraction",H17,IF(H17=1,1,H17*0.9)) -> 1
C73: Efectividad en incidencia | D73: =IF($C18="Affected fraction",D18,IF(D18=1,1,D18*0.9)) -> 0 | E73: =IF($C18="Affected fraction",E18,IF(E18=1,1,E18*0.9)) -> 0 | F73: 0 | G73: 0 | H73: 0
B74: MAM | C74: Fracción afectada | D74: =IF($C19="Affected fraction",D19,IF(D19=1,1,D19*0.9)) -> 0 | E74: =IF($C19="Affected fraction",E19,IF(E19=1,1,E19*0.9)) -> 0 | F74: 1 | G74: 1 | H74: 1
C75: Efectividad en incidencia | D75: =IF($C20="Affected fraction",D20,IF(D20=1,1,D20*0.9)) -> 0 | E75: =IF($C20="Affected fraction",E20,IF(E20=1,1,E20*0.9)) -> 0 | F75: 0 | G75: 0 | H75: 0
A76: Enriquecimiento de la harina de trigo con hierro y ácido fólico | B76: Anomalías congénitas neonatales | C76: Fracción afectada | D76: =IF($C21="Affected fraction",D21,IF(D21=1,1,D21*0.9)) -> 1 | E76: =IF($C21="Affected fraction",E21,IF(E21=1,1,E21*0.9)) -> 0 | F76: =IF($C21="Affected fraction",F21,IF(F21=1,1,F21*0.9)) -> 0 | G76: =IF($C21="Affected fraction",G21,IF(G21=1,1,G21*0.9)) -> 0 | H76: =IF($C21="Affected fraction",H21,IF(H21=1,1,H21*0.9)) -> 0
C77: Efectividad en mortalidad | D77: 0.11 | E77: =IF($C22="Affected fraction",E22,IF(E22=1,1,E22*0.9)) -> 0 | F77: =IF($C22="Affected fraction",F22,IF(F22=1,1,F22*0.9)) -> 0 | G77: =IF($C22="Affected fraction",G22,IF(G22=1,1,G22*0.9)) -> 0 | H77: =IF($C22="Affected fraction",H22,IF(H22=1,1,H22*0.9)) -> 0
A78: Enriquecimiento del maíz con hierro y ácido fólico | B78: Anomalías congénitas neonatales | C78: Fracción afectada | D78: =IF($C23="Affected fraction",D23,IF(D23=1,1,D23*0.9)) -> 1 | E78: =IF($C23="Affected fraction",E23,IF(E23=1,1,E23*0.9)) -> 0 | F78: =IF($C23="Affected fraction",F23,IF(F23=1,1,F23*0.9)) -> 0 | G78: =IF($C23="Affected fraction",G23,IF(G23=1,1,G23*0.9)) -> 0 | H78: =IF($C23="Affected fraction",H23,IF(H23=1,1,H23*0.9)) -> 0
C79: Efectividad en mortalidad | D79: 0.11 | E79: =IF($C24="Affected fraction",E24,IF(E24=1,1,E24*0.9)) -> 0 | F79: =IF($C24="Affected fraction",F24,IF(F24=1,1,F24*0.9)) -> 0 | G79: =IF($C24="Affected fraction",G24,IF(G24=1,1,G24*0.9)) -> 0 | H79: =IF($C24="Affected fraction",H24,IF(H24=1,1,H24*0.9)) -> 0
A80: Enriquecimiento del arroz con hierro y ácido fólico | B80: Anomalías congénitas neonatales | C80: Fracción afectada | D80: =IF($C25="Affected fraction",D25,IF(D25=1,1,D25*0.9)) -> 1 | E80: =IF($C25="Affected fraction",E25,IF(E25=1,1,E25*0.9)) -> 0 | F80: =IF($C25="Affected fraction",F25,IF(F25=1,1,F25*0.9)) -> 0 | G80: =IF($C25="Affected fraction",G25,IF(G25=1,1,G25*0.9)) -> 0 | H80: =IF($C25="Affected fraction",H25,IF(H25=1,1,H25*0.9)) -> 0
C81: Efectividad en mortalidad | D81: 0.11 | E81: =IF($C26="Affected fraction",E26,IF(E26=1,1,E26*0.9)) -> 0 | F81: =IF($C26="Affected fraction",F26,IF(F26=1,1,F26*0.9)) -> 0 | G81: =IF($C26="Affected fraction",G26,IF(G26=1,1,G26*0.9)) -> 0 | H81: =IF($C26="Affected fraction",H26,IF(H26=1,1,H26*0.9)) -> 0
A82: WASH: Mejora de la fuente de agua | B82: Diarrea | C82: Fracción afectada | D82: 1 | E82: 1 | F82: 1 | G82: 1 | H82: 1
C83: Efectividad en mortalidad | D83: 0.07 | E83: 0.07 | F83: 0.07 | G83: 0.07 | H83: 0.07
C84: Efectividad en incidencia | D84: 0 | E84: 0 | F84: 0 | G84: 0 | H84: 0
A85: WASH: Agua corriente o entubada | B85: Diarrea | C85: Fracción afectada | D85: 1 | E85: 1 | F85: 1 | G85: 1 | H85: 1
C86: Efectividad en mortalidad | D86: 0 | E86: 0 | F86: 0 | G86: 0 | H86: 0
C87: Efectividad en incidencia | D87: 0 | E87: 0 | F87: 0 | G87: 0 | H87: 0
A88: WASH: Mejora del saneamiento | B88: Diarrea | C88: Fracción afectada | D88: 1 | E88: 1 | F88: 1 | G88: 1 | H88: 1
C89: Efectividad en mortalidad | D89: 0 | E89: 0 | F89: 0 | G89: 0 | H89: 0
C90: Efectividad en incidencia | D90: 0 | E90: 0 | F90: 0 | G90: 0 | H90: 0
A91: WASH: Eliminación higiénica de residuos | B91: Diarrea | C91: Fracción afectada | D91: 1 | E91: 1 | F91: 1 | G91: 1 | H91: 1
C92: Efectividad en mortalidad | D92: 0 | E92: 0 | F92: 0 | G92: 0 | H92: 0
C93: Efectividad en incidencia | D93: 0 | E93: 0 | F93: 0 | G93: 0 | H93: 0
A94: WASH: Lavado de manos | B94: Diarrea | C94: Fracción afectada | D94: 1 | E94: 1 | F94: 1 | G94: 1 | H94: 1
C95: Efectividad en mortalidad | D95: 0 | E95: 0 | F95: 0 | G95: 0 | H95: 0
C96: Efectividad en incidencia | D96: 0 | E96: 0 | F96: 0 | G96: 0 | H96: 0
A97: Suplementación con zinc | B97: Diarrea | C97: Fracción afectada | D97: =IF($C42="Affected fraction",D42,IF(D42=1,1,D42*0.9)) -> 0 | E97: =IF($C42="Affected fraction",E42,IF(E42=1,1,E42*0.9)) -> 1 | F97: =IF($C42="Affected fraction",F42,IF(F42=1,1,F42*0.9)) -> 1 | G97: =IF($C42="Affected fraction",G42,IF(G42=1,1,G42*0.9)) -> 1 | H97: =IF($C42="Affected fraction",H42,IF(H42=1,1,H42*0.9)) -> 1
C98: Efectividad en mortalidad | D98: 0 | E98: 0 | F98: 0 | G98: 0 | H98: 0
C99: Efectividad en incidencia | D99: 0.07 | E99: 0.07 | F99: 0.07 | G99: 0.07 | H99: 0.07
B100: Neumonía | C100: Fracción afectada | D100: 0 | E100: 1 | F100: 1 | G100: 1 | H100: 1
C101: Efectividad en mortalidad | D101: 0 | E101: 0 | F101: 0 | G101: 0 | H101: 0
...

Sheet Prog. para mujeres embarazadas
A1: Programa | B1: Condición objetivo | D1: PW: 15-19 años | E1: PW: 20-29 años | F1: PW: 30-39 años | G1: PW: 40-49 años
A2: Suplemento con calcio | B2: Trastornos hipertensivos | C2: Fracción afectada | D2: 1 | E2: 1 | F2: 1 | G2: 1
C3: Efectividad en mortalidad | D3: 0 | E3: 0 | F3: 0 | G3: 0
A4: Magnesio para la preeclampsia | B4: Trastornos hipertensivos | C4: Fracción afectada | D4: 1 | E4: 1 | F4: 1 | G4: 1
C5: Efectividad en mortalidad | D5: 0.59 | E5: 0.59 | F5: 0.59 | G5: 0.59
A6: Magnesio para la eclampsia | B6: Trastornos hipertensivos | C6: Fracción afectada | D6: 1 | E6: 1 | F6: 1 | G6: 1
C7: Efectividad en mortalidad | D7: 0.59 | E7: 0.59 | F7: 0.59 | G7: 0.59
A8: Suplementación con micronutrientes múltiples | B8: Mortinatos | C8: Fracción afectada | D8: 1 | E8: 1 | F8: 1 | G8: 1
C9: Efectividad | D9: 0.09 | E9: 0.09 | F9: 0.09 | G9: 0.09
A11: Límite inferior
A12: Programa | B12: Condición objetivo | D12: PW: 15-19 años | E12: PW: 20-29 años | F12: PW: 30-39 años | G12: PW: 40-49 años
A13: Suplemento con calcio | B13: Trastornos hipertensivos | C13: Fracción afectada | D13: =IF($C2="Affected fraction",D2,IF(D2=1,1,D2*0.9)) -> 1 | E13: =IF($C2="Affected fraction",E2,IF(E2=1,1,E2*0.9)) -> 1 | F13: =IF($C2="Affected fraction",F2,IF(F2=1,1,F2*0.9)) -> 1 | G13: =IF($C2="Affected fraction",G2,IF(G2=1,1,G2*0.9)) -> 1
C14: Efectividad en mortalidad | D14: 0 | E14: 0 | F14: 0 | G14: 0
A15: Magnesio para la preeclampsia | B15: Trastornos hipertensivos | C15: Fracción afectada | D15: =IF($C4="Affected fraction",D4,IF(D4=1,1,D4*0.9)) -> 1 | E15: =IF($C4="Affected fraction",E4,IF(E4=1,1,E4*0.9)) -> 1 | F15: =IF($C4="Affected fraction",F4,IF(F4=1,1,F4*0.9)) -> 1 | G15: =IF($C4="Affected fraction",G4,IF(G4=1,1,G4*0.9)) -> 1
C16: Efectividad en mortalidad | D16: =IF($C5="Affected fraction",D5,IF(D5=1,1,D5*0.9)) -> 0.531 | E16: =IF($C5="Affected fraction",E5,IF(E5=1,1,E5*0.9)) -> 0.531 | F16: =IF($C5="Affected fraction",F5,IF(F5=1,1,F5*0.9)) -> 0.531 | G16: =IF($C5="Affected fraction",G5,IF(G5=1,1,G5*0.9)) -> 0.531
A17: Magnesio para la eclampsia | B17: Trastornos hipertensivos | C17: Fracción afectada | D17: =IF($C6="Affected fraction",D6,IF(D6=1,1,D6*0.9)) -> 1 | E17: =IF($C6="Affected fraction",E6,IF(E6=1,1,E6*0.9)) -> 1 | F17: =IF($C6="Affected fraction",F6,IF(F6=1,1,F6*0.9)) -> 1 | G17: =IF($C6="Affected fraction",G6,IF(G6=1,1,G6*0.9)) -> 1
C18: Efectividad en mortalidad | D18: =IF($C7="Affected fraction",D7,IF(D7=1,1,D7*0.9)) -> 0.531 | E18: =IF($C7="Affected fraction",E7,IF(E7=1,1,E7*0.9)) -> 0.531 | F18: =IF($C7="Affected fraction",F7,IF(F7=1,1,F7*0.9)) -> 0.531 | G18: =IF($C7="Affected fraction",G7,IF(G7=1,1,G7*0.9)) -> 0.531
A19: Suplementación con micronutrientes múltiples | B19: Mortinatos | C19: Fracción afectada | D19: =IF($C8="Affected fraction",D8,IF(D8=1,1,D8*0.9)) -> 1 | E19: =IF($C8="Affected fraction",E8,IF(E8=1,1,E8*0.9)) -> 1 | F19: =IF($C8="Affected fraction",F8,IF(F8=1,1,F8*0.9)) -> 1 | G19: =IF($C8="Affected fraction",G8,IF(G8=1,1,G8*0.9)) -> 1
C20: Efectividad | D20: 0.02 | E20: 0.02 | F20: 0.02 | G20: 0.02
A22: Límite superior
A23: Programa | B23: Condición objetivo | D23: PW: 15-19 años | E23: PW: 20-29 años | F23: PW: 30-39 años | G23: PW: 40-49 años
A24: Suplemento con calcio | B24: Trastornos hipertensivos | C24: Fracción afectada | D24: =IF($C2="Affected fraction",D2,IF(D2=1,1,D2*1.05)) -> 1 | E24: =IF($C2="Affected fraction",E2,IF(E2=1,1,E2*1.05)) -> 1 | F24: =IF($C2="Affected fraction",F2,IF(F2=1,1,F2*1.05)) -> 1 | G24: =IF($C2="Affected fraction",G2,IF(G2=1,1,G2*1.05)) -> 1
C25: Efectividad en mortalidad | D25: 0 | E25: 0 | F25: 0 | G25: 0
A26: Magnesio para la preeclampsia | B26: Trastornos hipertensivos | C26: Fracción afectada | D26: =IF($C4="Affected fraction",D4,IF(D4=1,1,D4*1.05)) -> 1 | E26: =IF($C4="Affected fraction",E4,IF(E4=1,1,E4*1.05)) -> 1 | F26: =IF($C4="Affected fraction",F4,IF(F4=1,1,F4*1.05)) -> 1 | G26: =IF($C4="Affected fraction",G4,IF(G4=1,1,G4*1.05)) -> 1
C27: Efectividad en mortalidad | D27: =IF($C5="Affected fraction",D5,IF(D5=1,1,D5*1.1)) -> 0.649 | E27: =IF($C5="Affected fraction",E5,IF(E5=1,1,E5*1.1)) -> 0.649 | F27: =IF($C5="Affected fraction",F5,IF(F5=1,1,F5*1.1)) -> 0.649 | G27: =IF($C5="Affected fraction",G5,IF(G5=1,1,G5*1.1)) -> 0.649
A28: Magnesio para la eclampsia | B28: Trastornos hipertensivos | C28: Fracción afectada | D28: =IF($C6="Affected fraction",D6,IF(D6=1,1,D6*1.05)) -> 1 | E28: =IF($C6="Affected fraction",E6,IF(E6=1,1,E6*1.05)) -> 1 | F28: =IF($C6="Affected fraction",F6,IF(F6=1,1,F6*1.05)) -> 1 | G28: =IF($C6="Affected fraction",G6,IF(G6=1,1,G6*1.05)) -> 1
C29: Efectividad en mortalidad | D29: =IF($C7="Affected fraction",D7,IF(D7=1,1,D7*1.1)) -> 0.649 | E29: =IF($C7="Affected fraction",E7,IF(E7=1,1,E7*1.1)) -> 0.649 | F29: =IF($C7="Affected fraction",F7,IF(F7=1,1,F7*1.1)) -> 0.649 | G29: =IF($C7="Affected fraction",G7,IF(G7=1,1,G7*1.1)) -> 0.649
A30: Suplementación con micronutrientes múltiples | B30: Mortinatos | C30: Fracción afectada | D30: =IF($C8="Affected fraction",D8,IF(D8=1,1,D8*1.05)) -> 1 | E30: =IF($C8="Affected fraction",E8,IF(E8=1,1,E8*1.05)) -> 1 | F30: =IF($C8="Affected fraction",F8,IF(F8=1,1,F8*1.05)) -> 1 | G30: =IF($C8="Affected fraction",G8,IF(G8=1,1,G8*1.05)) -> 1
C31: Efectividad | D31: 0.14 | E31: 0.14 | F31: 0.14 | G31: 0.14
